{
  "student_information": {
    "register_number": "19BEC1007",
    "name": "AYUSH RANJAN ROY"
  },
  "tables": {
    "grade_history_combined": [
      {
        "Slno": "1",
        "CourseCode": "CSE1001",
        "CourseTitle": "Problem Solving and Programming",
        "CourseType": "LO",
        "Credits": "3.0",
        "Grade": "B",
        "ExamMonth": "Nov-2019",
        "ResultDeclaredOn": "08-Feb-2020",
        "CourseOption": "NIL",
        "CourseDistribUtion": "UC"
      },
      {
        "Slno": "2",
        "CourseCode": "ECE1001",
        "CourseTitle": "Fundamentals of Electrical Circuits",
        "CourseType": "ETL",
        "Credits": "3.0",
        "Grade": "B",
        "ExamMonth": "Nov-2019",
        "ResultDeclaredOn": "08-Feb-2020",
        "CourseOption": "NIL",
        "CourseDistribUtion": "PC"
      },
      {
        "Slno": "3",
        "CourseCode": "ENG1902",
        "CourseTitle": "Technical English - II",
        "CourseType": "LO",
        "Credits": "2.0",
        "Grade": "N2",
        "ExamMonth": "Nov-2019",
        "ResultDeclaredOn": "08-Feb-2020",
        "CourseOption": "NIL",
        "CourseDistribUtion": "UC"
      },
      {
        "Slno": "4",
        "CourseCode": "ENG1902",
        "CourseTitle": "Technical English - II",
        "CourseType": "LO",
        "Credits": "2.0",
        "Grade": "B",
        "ExamMonth": "L Jul-2021",
        "ResultDeclaredOn": "18-Aug-2021",
        "CourseOption": "NIL",
        "CourseDistribUtion": "UC"
      },
      {
        "Slno": "5",
        "CourseCode": "HUM1021",
        "CourseTitle": "Ethics and Values",
        "CourseType": "TH",
        "Credits": "2.0",
        "Grade": "B",
        "ExamMonth": "Nov-2019",
        "ResultDeclaredOn": "08-Feb-2020",
        "CourseOption": "NIL",
        "CourseDistribUtion": "UC"
      },
      {
        "Slno": "6",
        "CourseCode": "MAT1011",
        "CourseTitle": "Calculus for Engineers",
        "CourseType": "ETL",
        "Credits": "4.0",
        "Grade": "C",
        "ExamMonth": "Nov-2019",
        "ResultDeclaredOn": "08-Feb-2020",
        "CourseOption": "NIL",
        "CourseDistribUtion": "UC"
      },
      {
        "Slno": "7",
        "CourseCode": "PHY1701",
        "CourseTitle": "Engineering Physics",
        "CourseType": "ETL",
        "Credits": "4.0",
        "Grade": "A N",
        "ExamMonth": "Nov-2019",
        "ResultDeclaredOn": "08-Feb-2020",
        "CourseOption": "NIL",
        "CourseDistribUtion": "UC"
      },
      {
        "Slno": "8",
        "CourseCode": "PHY1701",
        "CourseTitle": "Engineering Physics",
        "CourseType": "ETL",
        "Credits": "4.0",
        "Grade": "A",
        "ExamMonth": "Jun-2021",
        "ResultDeclaredOn": "21-Jul-2021",
        "CourseOption": "NIL",
        "CourseDistribUtion": "UC"
      },
      {
        "Slno": "9",
        "CourseCode": "STS1201",
        "CourseTitle": "Introduction to Problem Solving",
        "CourseType": "SS",
        "Credits": "1.0",
        "Grade": "I B",
        "ExamMonth": "Nov-2019",
        "ResultDeclaredOn": "17-Feb-2020",
        "CourseOption": "NIL",
        "CourseDistribUtion": "UC"
      },
      {
        "Slno": "10",
        "CourseCode": "CHY1002",
        "CourseTitle": "Environmental Sciences",
        "CourseType": "TH",
        "Credits": "3.0",
        "Grade": "C",
        "ExamMonth": "Jun-2020",
        "ResultDeclaredOn": "16-Jun-2020",
        "CourseOption": "NC",
        "CourseDistribUtion": "NC"
      },
      {
        "Slno": "11",
        "CourseCode": "CHY1701",
        "CourseTitle": "Engineering Chemistry",
        "CourseType": "ETL",
        "Credits": "C 4.0",
        "Grade": "B",
        "ExamMonth": "Jun-2020",
        "ResultDeclaredOn": "16-Jun-2020",
        "CourseOption": "NIL",
        "CourseDistribUtion": "UC"
      },
      {
        "Slno": "12",
        "CourseCode": "CSE1002",
        "CourseTitle": "Problem Solving and Object Oriented Programming",
        "CourseType": "LO",
        "Credits": "I 3.0",
        "Grade": "B",
        "ExamMonth": "Jun-2020",
        "ResultDeclaredOn": "16-Jun-2020",
        "CourseOption": "NIL",
        "CourseDistribUtion": "UC"
      },
      {
        "Slno": "13",
        "CourseCode": "ECE1002",
        "CourseTitle": "Semiconductor Devices and Circuits",
        "CourseType": "ETL",
        "Credits": "F 4.0",
        "Grade": "B",
        "ExamMonth": "Jun-2020",
        "ResultDeclaredOn": "16-Jun-2020",
        "CourseOption": "NIL",
        "CourseDistribUtion": "PC"
      },
      {
        "Slno": "14",
        "CourseCode": "ECE1005",
        "CourseTitle": "Sensors and Instrumentation",
        "CourseType": "ETP",
        "Credits": "2.0",
        "Grade": "B",
        "ExamMonth": "Jun-2020",
        "ResultDeclaredOn": "16-Jun-2020",
        "CourseOption": "NIL",
        "CourseDistribUtion": "PC"
      },
      {
        "Slno": "15",
        "CourseCode": "FRE1001",
        "CourseTitle": "Francais quotidien",
        "CourseType": "F TH",
        "Credits": "2.0",
        "Grade": "C",
        "ExamMonth": "Jun-2020",
        "ResultDeclaredOn": "16-Jun-2020",
        "CourseOption": "NIL",
        "CourseDistribUtion": "UC"
      },
      {
        "Slno": "16",
        "CourseCode": "MAT2002",
        "CourseTitle": "O Applications of Differential and Difference Equations",
        "CourseType": "ETL",
        "Credits": "4.0",
        "Grade": "B",
        "ExamMonth": "Jun-2020",
        "ResultDeclaredOn": "16-Jun-2020",
        "CourseOption": "NIL",
        "CourseDistribUtion": "PC"
      },
      {
        "Slno": "17",
        "CourseCode": "ONL1021",
        "CourseTitle": "Essentials of Machine Learning",
        "CourseType": "OC",
        "Credits": "4.0",
        "Grade": "B",
        "ExamMonth": "Jun-2020",
        "ResultDeclaredOn": "12-Aug-2020",
        "CourseOption": "NIL",
        "CourseDistribUtion": "UE"
      },
      {
        "Slno": "18",
        "CourseCode": "PHY1901",
        "CourseTitle": "N Introduction to Innovative Projects",
        "CourseType": "TH",
        "Credits": "1.0",
        "Grade": "A",
        "ExamMonth": "Jun-2020",
        "ResultDeclaredOn": "19-Jun-2020",
        "CourseOption": "NIL",
        "CourseDistribUtion": "UC"
      },
      {
        "Slno": "19",
        "CourseCode": "STS1202",
        "CourseTitle": "U Introduction to Quantitative, Logical and Verbal Ability",
        "CourseType": "SS",
        "Credits": "1.0",
        "Grade": "C",
        "ExamMonth": "Jun-2020",
        "ResultDeclaredOn": "24-Jun-2020",
        "CourseOption": "NIL",
        "CourseDistribUtion": "UC"
      },
      {
        "Slno": "20",
        "CourseCode": "CSE2001",
        "CourseTitle": "Computer Architecture and Organization",
        "CourseType": "TH",
        "Credits": "3.0",
        "Grade": "B",
        "ExamMonth": "Jan-2021",
        "ResultDeclaredOn": "26-Feb-2021",
        "CourseOption": "NIL",
        "CourseDistribUtion": "UE"
      },
      {
        "Slno": "21",
        "CourseCode": "ECE1003",
        "CourseTitle": "Electromagnetic Field Theory",
        "CourseType": "TH",
        "Credits": "3.0",
        "Grade": "E",
        "ExamMonth": "Jan-2021",
        "ResultDeclaredOn": "26-Feb-2021",
        "CourseOption": "NIL",
        "CourseDistribUtion": "PC"
      },
      {
        "Slno": "22",
        "CourseCode": "ECE1004",
        "CourseTitle": "Signals and Systems",
        "CourseType": "ETP",
        "Credits": "3.0",
        "Grade": "C",
        "ExamMonth": "Jan-2021",
        "ResultDeclaredOn": "26-Feb-2021",
        "CourseOption": "NIL",
        "CourseDistribUtion": "PC"
      },
      {
        "Slno": "23",
        "CourseCode": "ECE2001",
        "CourseTitle": "Network Theory",
        "CourseType": "TH",
        "Credits": "3.0",
        "Grade": "N1",
        "ExamMonth": "Jan-2021",
        "ResultDeclaredOn": "26-Feb-2021",
        "CourseOption": "NIL",
        "CourseDistribUtion": "PC"
      },
      {
        "Slno": "24",
        "CourseCode": "ECE2001",
        "CourseTitle": "Network Theory",
        "CourseType": "TH",
        "Credits": "3.0",
        "Grade": "C",
        "ExamMonth": "Jul-2021",
        "ResultDeclaredOn": "11-Aug-2021",
        "CourseOption": "NIL",
        "CourseDistribUtion": "PC"
      },
      {
        "Slno": "25",
        "CourseCode": "ECE2002",
        "CourseTitle": "Analog Electronic Circuits",
        "CourseType": "ETLP",
        "Credits": "4.0",
        "Grade": "E",
        "ExamMonth": "Jan-2021",
        "ResultDeclaredOn": "18-Mar-2021",
        "CourseOption": "NIL",
        "CourseDistribUtion": "PC"
      },
      {
        "Slno": "26",
        "CourseCode": "ECE2003",
        "CourseTitle": "Digital Logic Design",
        "CourseType": "ETL",
        "Credits": "3.0",
        "Grade": "D",
        "ExamMonth": "Jan-2021",
        "ResultDeclaredOn": "26-Feb-2021",
        "CourseOption": "NIL",
        "CourseDistribUtion": "PC"
      },
      {
        "Slno": "27",
        "CourseCode": "MAT2001",
        "CourseTitle": "Statistics for Engineers",
        "CourseType": "ETL",
        "Credits": "4.0",
        "Grade": "C",
        "ExamMonth": "Jan-2021",
        "ResultDeclaredOn": "26-Feb-2021",
        "CourseOption": "NIL",
        "CourseDistribUtion": "UC"
      },
      {
        "Slno": "28",
        "CourseCode": "MGT1022",
        "CourseTitle": "Lean Start-up Management",
        "CourseType": "ETP",
        "Credits": "2.0",
        "Grade": "A",
        "ExamMonth": "Jan-2021",
        "ResultDeclaredOn": "26-Feb-2021",
        "CourseOption": "NIL",
        "CourseDistribUtion": "UC"
      },
      {
        "Slno": "29",
        "CourseCode": "STS2201",
        "CourseTitle": "Numerical Ability and Cognitive Intelligence",
        "CourseType": "SS",
        "Credits": "1.0",
        "Grade": "A",
        "ExamMonth": "Jan-2021",
        "ResultDeclaredOn": "26-Feb-2021",
        "CourseOption": "NIL",
        "CourseDistribUtion": "UC"
      },
      {
        "Slno": "30",
        "CourseCode": "CSE2003",
        "CourseTitle": "Data Structures and Algorithms",
        "CourseType": "ETLP",
        "Credits": "4.0",
        "Grade": "C",
        "ExamMonth": "Jun-2021",
        "ResultDeclaredOn": "21-Jul-2021",
        "CourseOption": "NIL",
        "CourseDistribUtion": "PE"
      },
      {
        "Slno": "31",
        "CourseCode": "ECE2004",
        "CourseTitle": "Transmission Lines and Waveguides",
        "CourseType": "TH",
        "Credits": "3.0",
        "Grade": "B",
        "ExamMonth": "Jun-2021",
        "ResultDeclaredOn": "21-Jul-2021",
        "CourseOption": "NIL",
        "CourseDistribUtion": "PC"
      },
      {
        "Slno": "32",
        "CourseCode": "ECE2005",
        "CourseTitle": "Probability Theory and Random Processes",
        "CourseType": "TH",
        "Credits": "3.0",
        "Grade": "B",
        "ExamMonth": "Jun-2021",
        "ResultDeclaredOn": "21-Jul-2021",
        "CourseOption": "NIL",
        "CourseDistribUtion": "PC"
      },
      {
        "Slno": "33",
        "CourseCode": "ECE2008",
        "CourseTitle": "Robotics and Automation",
        "CourseType": "ETP",
        "Credits": "3.0",
        "Grade": "A",
        "ExamMonth": "Jun-2021",
        "ResultDeclaredOn": "21-Jul-2021",
        "CourseOption": "NIL",
        "CourseDistribUtion": "PE"
      },
      {
        "Slno": "34",
        "CourseCode": "ECE3001",
        "CourseTitle": "Analog Communication Systems",
        "CourseType": "ETL",
        "Credits": "4.0",
        "Grade": "B",
        "ExamMonth": "L Jun-2021",
        "ResultDeclaredOn": "21-Jul-2021",
        "CourseOption": "NIL",
        "CourseDistribUtion": "PC"
      },
      {
        "Slno": "35",
        "CourseCode": "ECE3003",
        "CourseTitle": "Microcontroller and its Applications",
        "CourseType": "ETLP",
        "Credits": "4.0",
        "Grade": "B",
        "ExamMonth": "Jun-2021",
        "ResultDeclaredOn": "21-Jul-2021",
        "CourseOption": "NIL",
        "CourseDistribUtion": "PC"
      },
      {
        "Slno": "36",
        "CourseCode": "EXC1219",
        "CourseTitle": "VIT Finance and Management Club",
        "CourseType": "ECA",
        "Credits": "2.0",
        "Grade": "A P",
        "ExamMonth": "Jun-2021",
        "ResultDeclaredOn": "19-Aug-2021",
        "CourseOption": "NC",
        "CourseDistribUtion": "NC"
      },
      {
        "Slno": "37",
        "CourseCode": "MAT3004",
        "CourseTitle": "Applied Linear Algebra",
        "CourseType": "TH",
        "Credits": "4.0",
        "Grade": "I B",
        "ExamMonth": "Jun-2021",
        "ResultDeclaredOn": "21-Jul-2021",
        "CourseOption": "NIL",
        "CourseDistribUtion": "PC"
      },
      {
        "Slno": "38",
        "CourseCode": "STS2202",
        "CourseTitle": "Advanced Aptitude and Reasoning Skills",
        "CourseType": "SS",
        "Credits": "1.0",
        "Grade": "B",
        "ExamMonth": "Jun-2021",
        "ResultDeclaredOn": "21-Jul-2021",
        "CourseOption": "NIL",
        "CourseDistribUtion": "UC"
      },
      {
        "Slno": "39",
        "CourseCode": "CSE3013",
        "CourseTitle": "Artificial Intelligence",
        "CourseType": "ETP",
        "Credits": "C 4.0",
        "Grade": "D",
        "ExamMonth": "Dec-2021",
        "ResultDeclaredOn": "29-Jan-2022",
        "CourseOption": "NIL",
        "CourseDistribUtion": "UE"
      },
      {
        "Slno": "40",
        "CourseCode": "CSE3501",
        "CourseTitle": "Information Security Analysis and Audit",
        "CourseType": "ETLP",
        "Credits": "I 4.0",
        "Grade": "C",
        "ExamMonth": "Dec-2021",
        "ResultDeclaredOn": "29-Jan-2022",
        "CourseOption": "NIL",
        "CourseDistribUtion": "PE"
      },
      {
        "Slno": "41",
        "CourseCode": "ECE2006",
        "CourseTitle": "Digital Signal Processing",
        "CourseType": "ETLP",
        "Credits": "4.0",
        "Grade": "D",
        "ExamMonth": "Dec-2021",
        "ResultDeclaredOn": "29-Jan-2022",
        "CourseOption": "NIL",
        "CourseDistribUtion": "PC"
      },
      {
        "Slno": "42",
        "CourseCode": "ECE3002",
        "CourseTitle": "VLSI System Design",
        "CourseType": "ETL",
        "Credits": "F 4.0",
        "Grade": "D",
        "ExamMonth": "Dec-2021",
        "ResultDeclaredOn": "29-Jan-2022",
        "CourseOption": "NIL",
        "CourseDistribUtion": "PC"
      },
      {
        "Slno": "43",
        "CourseCode": "ECE3010",
        "CourseTitle": "Antennas and Wave Propagation",
        "CourseType": "TH",
        "Credits": "3.0",
        "Grade": "D",
        "ExamMonth": "Dec-2021",
        "ResultDeclaredOn": "29-Jan-2022",
        "CourseOption": "NIL",
        "CourseDistribUtion": "PE"
      },
      {
        "Slno": "44",
        "CourseCode": "ECE4001",
        "CourseTitle": "Digital Communication Systems",
        "CourseType": "F ETL",
        "Credits": "4.0",
        "Grade": "B",
        "ExamMonth": "Dec-2021",
        "ResultDeclaredOn": "29-Jan-2022",
        "CourseOption": "NIL",
        "CourseDistribUtion": "PC"
      },
      {
        "Slno": "45",
        "CourseCode": "STS3401",
        "CourseTitle": "O Foundation to Programming Skills",
        "CourseType": "SS",
        "Credits": "1.0",
        "Grade": "B",
        "ExamMonth": "Dec-2021",
        "ResultDeclaredOn": "29-Jan-2022",
        "CourseOption": "NIL",
        "CourseDistribUtion": "UC"
      },
      {
        "Slno": "46",
        "CourseCode": "CSE2005",
        "CourseTitle": "Operating Systems",
        "CourseType": "ETLP",
        "Credits": "4.0",
        "Grade": "A",
        "ExamMonth": "May-2022",
        "ResultDeclaredOn": "06-Jun-2022",
        "CourseOption": "NIL",
        "CourseDistribUtion": "PE"
      },
      {
        "Slno": "47",
        "CourseCode": "CSE3502",
        "CourseTitle": "Information Security Management",
        "CourseType": "ETLP",
        "Credits": "4.0",
        "Grade": "B",
        "ExamMonth": "May-2022",
        "ResultDeclaredOn": "06-Jun-2022",
        "CourseOption": "NIL",
        "CourseDistribUtion": "PE"
      },
      {
        "Slno": "48",
        "CourseCode": "ECE1901",
        "CourseTitle": "N Technical Answers for Real World Problems (TARP)",
        "CourseType": "ETP",
        "Credits": "2.0",
        "Grade": "A",
        "ExamMonth": "May-2022",
        "ResultDeclaredOn": "06-Jun-2022",
        "CourseOption": "NIL",
        "CourseDistribUtion": "UC"
      },
      {
        "Slno": "49",
        "CourseCode": "ECE4009",
        "CourseTitle": "U Wireless and Mobile Communication",
        "CourseType": "ETLP",
        "Credits": "5.0",
        "Grade": "B",
        "ExamMonth": "May-2022",
        "ResultDeclaredOn": "06-Jun-2022",
        "CourseOption": "NIL",
        "CourseDistribUtion": "PE"
      },
      {
        "Slno": "50",
        "CourseCode": "EEE1003",
        "CourseTitle": "Electrical Workshop",
        "CourseType": "LO",
        "Credits": "1.0",
        "Grade": "B",
        "ExamMonth": "May-2022",
        "ResultDeclaredOn": "06-Jun-2022",
        "CourseOption": "NIL",
        "CourseDistribUtion": "UE"
      },
      {
        "Slno": "51",
        "CourseCode": "MAT3005",
        "CourseTitle": "Applied Numerical Methods",
        "CourseType": "TH",
        "Credits": "4.0",
        "Grade": "B",
        "ExamMonth": "May-2022",
        "ResultDeclaredOn": "06-Jun-2022",
        "CourseOption": "NIL",
        "CourseDistribUtion": "PE"
      },
      {
        "Slno": "52",
        "CourseCode": "STS3205",
        "CourseTitle": "Advanced JAVA Programming",
        "CourseType": "SS",
        "Credits": "1.0",
        "Grade": "C",
        "ExamMonth": "May-2022",
        "ResultDeclaredOn": "06-Jun-2022",
        "CourseOption": "NIL",
        "CourseDistribUtion": "UC"
      },
      {
        "Slno": "53",
        "CourseCode": "ECE4007",
        "CourseTitle": "Information Theory and Coding",
        "CourseType": "ETP",
        "Credits": "4.0",
        "Grade": "B",
        "ExamMonth": "Aug-2022",
        "ResultDeclaredOn": "29-Aug-2022",
        "CourseOption": "NIL",
        "CourseDistribUtion": "PE"
      },
      {
        "Slno": "54",
        "CourseCode": "ECE4013",
        "CourseTitle": "Cryptography and Network Security",
        "CourseType": "TH",
        "Credits": "3.0",
        "Grade": "B",
        "ExamMonth": "Aug-2022",
        "ResultDeclaredOn": "29-Aug-2022",
        "CourseOption": "NIL",
        "CourseDistribUtion": "PE"
      },
      {
        "Slno": "55",
        "CourseCode": "ECE1903",
        "CourseTitle": "Comprehensive Examination",
        "CourseType": "PJT",
        "Credits": "1.0",
        "Grade": "F",
        "ExamMonth": "Nov-2022",
        "ResultDeclaredOn": "02-Mar-2023",
        "CourseOption": "NIL",
        "CourseDistribUtion": "UC"
      },
      {
        "Slno": "56",
        "CourseCode": "ECE1903",
        "CourseTitle": "Comprehensive Examination",
        "CourseType": "PJT",
        "Credits": "1.0",
        "Grade": "C",
        "ExamMonth": "Apr-2023",
        "ResultDeclaredOn": "09-May-2023",
        "CourseOption": "NIL",
        "CourseDistribUtion": "UC"
      },
      {
        "Slno": "57",
        "CourseCode": "ECE1902",
        "CourseTitle": "Industrial Internship",
        "CourseType": "PJT",
        "Credits": "1.0",
        "Grade": "S",
        "ExamMonth": "Apr-2023",
        "ResultDeclaredOn": "16-May-2023",
        "CourseOption": "NIL",
        "CourseDistribUtion": "UC"
      },
      {
        "Slno": "58",
        "CourseCode": "ECE1904",
        "CourseTitle": "Capstone Project",
        "CourseType": "PJT",
        "Credits": "12.0",
        "Grade": "A",
        "ExamMonth": "Apr-2023",
        "ResultDeclaredOn": "20-May-2023",
        "CourseOption": "NIL",
        "CourseDistribUtion": "UC"
      }
    ],
    "curriculum_details": [
      {
        "CurriculumDistributionType": "Programme Core",
        "CreditsRequired": "59.0",
        "CreditsEarned": "59.0"
      },
      {
        "CurriculumDistributionType": "Programme Elective",
        "CreditsRequired": "36.0",
        "CreditsEarned": "38.0"
      },
      {
        "CurriculumDistributionType": "University Core",
        "CreditsRequired": "L 53.0",
        "CreditsEarned": "53.0"
      },
      {
        "CurriculumDistributionType": "University Elective",
        "CreditsRequired": "12.0",
        "CreditsEarned": "12.0"
      },
      {
        "CurriculumDistributionType": "Bridge Course",
        "CreditsRequired": "A 4.0",
        "CreditsEarned": "0.0"
      },
      {
        "CurriculumDistributionType": "Non Credit Course",
        "CreditsRequired": "5.0",
        "CreditsEarned": "5.0"
      },
      {
        "CurriculumDistributionType": "Total Credits",
        "CreditsRequired": "160.0",
        "CreditsEarned": "167.0"
      }
    ],
    "c_basket_details": [
      {
        "BasketTitle": "Soft Skills",
        "DistributionType": "UC",
        "CreditsRequired": "6.0",
        "CreditsEarned": "6.0"
      },
      {
        "BasketTitle": "Co-Extra Curricular Basket",
        "DistributionType": "I NC",
        "CreditsRequired": "2.0",
        "CreditsEarned": "2.0"
      },
      {
        "BasketTitle": "Foreign Language Course Basket",
        "DistributionType": "F UC",
        "CreditsRequired": "2.0",
        "CreditsEarned": "2.0"
      }
    ],
    "f_cgpa_details": [
      {
        "CreditsRegistered": "162.0",
        "CreditsEarned": "162.0",
        "Cgpa": "7.67",
        "SGrades": "1",
        "AGrades": "O 8",
        "BGrades": "26",
        "CGrades": "10",
        "DGrades": "5",
        "EGrades": "2",
        "FGrades": "0",
        "NGrades": "0"
      }
    ]
  }
}