{
  "student_information": {
    "register_number": "21BFT1023",
    "name": "MOHAMMED FARIZ I"
  },
  "tables": {
    "grade_history_combined": [
      {
        "Slno": "1",
        "CourseCode": "BCSE101E",
        "CourseTitle": "Computer Programming: Python",
        "CourseType": "ETL",
        "Credits": "3.0",
        "Grade": "A",
        "ExamMonth": "Jan-2022",
        "ResultDeclaredOn": "22-Feb-2022",
        "CourseOption": "NIL",
        "CourseDistribUtion": "FCBES"
      },
      {
        "Slno": "2",
        "CourseCode": "BECE101L",
        "CourseTitle": "Basic Electronics",
        "CourseType": "TH",
        "Credits": "2.0",
        "Grade": "B",
        "ExamMonth": "Jan-2022",
        "ResultDeclaredOn": "22-Feb-2022",
        "CourseOption": "NIL",
        "CourseDistribUtion": "FCBES"
      },
      {
        "Slno": "3",
        "CourseCode": "BECE101P",
        "CourseTitle": "Basic Electronics Lab",
        "CourseType": "LO",
        "Credits": "1.0",
        "Grade": "A",
        "ExamMonth": "Jan-2022",
        "ResultDeclaredOn": "22-Feb-2022",
        "CourseOption": "NIL",
        "CourseDistribUtion": "FCBES"
      },
      {
        "Slno": "4",
        "CourseCode": "BENG101N",
        "CourseTitle": "Effective English Communication",
        "CourseType": "LO",
        "Credits": "2.0",
        "Grade": "B",
        "ExamMonth": "L Jan-2022",
        "ResultDeclaredOn": "22-Feb-2022",
        "CourseOption": "NIL",
        "CourseDistribUtion": "BC"
      },
      {
        "Slno": "5",
        "CourseCode": "BFST101N",
        "CourseTitle": "Introduction to Engineering",
        "CourseType": "PJT",
        "Credits": "1.0",
        "Grade": "P",
        "ExamMonth": "Jan-2022",
        "ResultDeclaredOn": "22-Feb-2022",
        "CourseOption": "NCPF",
        "CourseDistribUtion": "NGCR"
      },
      {
        "Slno": "6",
        "CourseCode": "BMAT100L",
        "CourseTitle": "Mathematics",
        "CourseType": "TH",
        "Credits": "4.0",
        "Grade": "A D",
        "ExamMonth": "Jan-2022",
        "ResultDeclaredOn": "22-Feb-2022",
        "CourseOption": "NIL",
        "CourseDistribUtion": "FCBS M"
      },
      {
        "Slno": "7",
        "CourseCode": "BPHY101L",
        "CourseTitle": "Engineering Physics",
        "CourseType": "TH",
        "Credits": "3.0",
        "Grade": "I B",
        "ExamMonth": "Jan-2022",
        "ResultDeclaredOn": "22-Feb-2022",
        "CourseOption": "NIL",
        "CourseDistribUtion": "FCBS M"
      },
      {
        "Slno": "8",
        "CourseCode": "BPHY101P",
        "CourseTitle": "Engineering Physics Lab",
        "CourseType": "LO",
        "Credits": "1.0",
        "Grade": "D",
        "ExamMonth": "Jan-2022",
        "ResultDeclaredOn": "22-Feb-2022",
        "CourseOption": "NIL",
        "CourseDistribUtion": "FCBS M"
      },
      {
        "Slno": "9",
        "CourseCode": "BSTS101P",
        "CourseTitle": "Quantitative Skills Practice I",
        "CourseType": "LO",
        "Credits": "C 1.5",
        "Grade": "C",
        "ExamMonth": "Jan-2022",
        "ResultDeclaredOn": "22-Feb-2022",
        "CourseOption": "NIL",
        "CourseDistribUtion": "FCHSS M"
      },
      {
        "Slno": "10",
        "CourseCode": "BCHY101L",
        "CourseTitle": "Engineering Chemistry",
        "CourseType": "TH",
        "Credits": "I 3.0",
        "Grade": "E",
        "ExamMonth": "Jun-2022",
        "ResultDeclaredOn": "29-Jul-2022",
        "CourseOption": "NIL",
        "CourseDistribUtion": "FCBS M"
      },
      {
        "Slno": "11",
        "CourseCode": "BCHY101P",
        "CourseTitle": "Engineering Chemistry Lab",
        "CourseType": "LO",
        "Credits": "F 1.0",
        "Grade": "A",
        "ExamMonth": "Jun-2022",
        "ResultDeclaredOn": "25-Jul-2022",
        "CourseOption": "NIL",
        "CourseDistribUtion": "FCBS M"
      },
      {
        "Slno": "12",
        "CourseCode": "BCSE103E",
        "CourseTitle": "Computer Programming: Java",
        "CourseType": "ETL",
        "Credits": "3.0",
        "Grade": "C",
        "ExamMonth": "Jun-2022",
        "ResultDeclaredOn": "25-Jul-2022",
        "CourseOption": "NIL",
        "CourseDistribUtion": "FCBES"
      },
      {
        "Slno": "13",
        "CourseCode": "BEEE101L",
        "CourseTitle": "Basic Electrical Engineering",
        "CourseType": "F TH",
        "Credits": "2.0",
        "Grade": "N1",
        "ExamMonth": "Jun-2022",
        "ResultDeclaredOn": "25-Jul-2022",
        "CourseOption": "NIL",
        "CourseDistribUtion": "FCBES"
      },
      {
        "Slno": "14",
        "CourseCode": "BEEE101L",
        "CourseTitle": "O Basic Electrical Engineering",
        "CourseType": "TH",
        "Credits": "2.0",
        "Grade": "B",
        "ExamMonth": "Apr-2023",
        "ResultDeclaredOn": "24-May-2023",
        "CourseOption": "NIL",
        "CourseDistribUtion": "FCBES"
      },
      {
        "Slno": "15",
        "CourseCode": "BEEE101P",
        "CourseTitle": "Basic Electrical Engineering Lab",
        "CourseType": "LO",
        "Credits": "1.0",
        "Grade": "A",
        "ExamMonth": "Jun-2022",
        "ResultDeclaredOn": "25-Jul-2022",
        "CourseOption": "NIL",
        "CourseDistribUtion": "FCBES"
      },
      {
        "Slno": "16",
        "CourseCode": "BENG101L",
        "CourseTitle": "N Technical English Communication",
        "CourseType": "TH",
        "Credits": "2.0",
        "Grade": "E",
        "ExamMonth": "Jun-2022",
        "ResultDeclaredOn": "25-Jul-2022",
        "CourseOption": "NIL",
        "CourseDistribUtion": "FCHSS M"
      },
      {
        "Slno": "17",
        "CourseCode": "BENG101P",
        "CourseTitle": "Technical English Communication Lab",
        "CourseType": "LO",
        "Credits": "1.0",
        "Grade": "C",
        "ExamMonth": "Jun-2022",
        "ResultDeclaredOn": "25-Jul-2022",
        "CourseOption": "NIL",
        "CourseDistribUtion": "FCHSS M"
      },
      {
        "Slno": "18",
        "CourseCode": "BFST101E",
        "CourseTitle": "U Foundation for Design",
        "CourseType": "ETL",
        "Credits": "3.0",
        "Grade": "C",
        "ExamMonth": "Jun-2022",
        "ResultDeclaredOn": "29-Jul-2022",
        "CourseOption": "NIL",
        "CourseDistribUtion": "FCBES"
      },
      {
        "Slno": "19",
        "CourseCode": "BHUM101N",
        "CourseTitle": "Ethics and Values",
        "CourseType": "OC",
        "Credits": "2.0",
        "Grade": "P",
        "ExamMonth": "Jun-2022",
        "ResultDeclaredOn": "25-Jul-2022",
        "CourseOption": "NCPF",
        "CourseDistribUtion": "NGCR"
      },
      {
        "Slno": "20",
        "CourseCode": "BMAT101L",
        "CourseTitle": "Calculus",
        "CourseType": "TH",
        "Credits": "3.0",
        "Grade": "N1",
        "ExamMonth": "Jun-2022",
        "ResultDeclaredOn": "25-Jul-2022",
        "CourseOption": "NIL",
        "CourseDistribUtion": "FCBS M"
      },
      {
        "Slno": "21",
        "CourseCode": "BMAT101L",
        "CourseTitle": "Calculus",
        "CourseType": "TH",
        "Credits": "3.0",
        "Grade": "N1",
        "ExamMonth": "Jan-2023",
        "ResultDeclaredOn": "24-Mar-2023",
        "CourseOption": "NIL",
        "CourseDistribUtion": "FCBS M"
      },
      {
        "Slno": "22",
        "CourseCode": "BMAT101L",
        "CourseTitle": "Calculus",
        "CourseType": "TH",
        "Credits": "3.0",
        "Grade": "B",
        "ExamMonth": "Aug-2023",
        "ResultDeclaredOn": "08-Sep-2023",
        "CourseOption": "NIL",
        "CourseDistribUtion": "FCBS M"
      },
      {
        "Slno": "23",
        "CourseCode": "BMAT101P",
        "CourseTitle": "Calculus Lab",
        "CourseType": "LO",
        "Credits": "1.0",
        "Grade": "D",
        "ExamMonth": "Jun-2022",
        "ResultDeclaredOn": "25-Jul-2022",
        "CourseOption": "NIL",
        "CourseDistribUtion": "FCBS M"
      },
      {
        "Slno": "24",
        "CourseCode": "BSTS102P",
        "CourseTitle": "Quantitative Skills Practice II",
        "CourseType": "SS",
        "Credits": "1.5",
        "Grade": "E",
        "ExamMonth": "Jun-2022",
        "ResultDeclaredOn": "25-Jul-2022",
        "CourseOption": "NIL",
        "CourseDistribUtion": "FCHSS M"
      },
      {
        "Slno": "25",
        "CourseCode": "BCHY102N",
        "CourseTitle": "Environmental Sciences",
        "CourseType": "OC",
        "Credits": "2.0",
        "Grade": "P",
        "ExamMonth": "Nov-2022",
        "ResultDeclaredOn": "10-Jan-2023",
        "CourseOption": "NCPF",
        "CourseDistribUtion": "NGCR"
      },
      {
        "Slno": "26",
        "CourseCode": "BENG102P",
        "CourseTitle": "Technical Report Writing",
        "CourseType": "LO",
        "Credits": "1.0",
        "Grade": "B",
        "ExamMonth": "Nov-2022",
        "ResultDeclaredOn": "10-Jan-2023",
        "CourseOption": "NIL",
        "CourseDistribUtion": "FCHSS M"
      },
      {
        "Slno": "27",
        "CourseCode": "BFST102L",
        "CourseTitle": "Textile Fibres",
        "CourseType": "TH",
        "Credits": "3.0",
        "Grade": "C",
        "ExamMonth": "Nov-2022",
        "ResultDeclaredOn": "10-Jan-2023",
        "CourseOption": "NIL",
        "CourseDistribUtion": "DLES"
      },
      {
        "Slno": "28",
        "CourseCode": "BFST102P",
        "CourseTitle": "Textile Fibres Lab",
        "CourseType": "LO",
        "Credits": "1.0",
        "Grade": "B",
        "ExamMonth": "Nov-2022",
        "ResultDeclaredOn": "10-Jan-2023",
        "CourseOption": "NIL",
        "CourseDistribUtion": "DLES"
      },
      {
        "Slno": "29",
        "CourseCode": "BFST103L",
        "CourseTitle": "Apparel Machineries",
        "CourseType": "TH",
        "Credits": "3.0",
        "Grade": "D",
        "ExamMonth": "Nov-2022",
        "ResultDeclaredOn": "10-Jan-2023",
        "CourseOption": "NIL",
        "CourseDistribUtion": "DLES"
      },
      {
        "Slno": "30",
        "CourseCode": "BFST103P",
        "CourseTitle": "Apparel Machineries Lab",
        "CourseType": "LO",
        "Credits": "1.0",
        "Grade": "B",
        "ExamMonth": "Nov-2022",
        "ResultDeclaredOn": "10-Jan-2023",
        "CourseOption": "NIL",
        "CourseDistribUtion": "DLES"
      },
      {
        "Slno": "31",
        "CourseCode": "BFST104L",
        "CourseTitle": "Fashion Studies",
        "CourseType": "TH",
        "Credits": "3.0",
        "Grade": "C",
        "ExamMonth": "Nov-2022",
        "ResultDeclaredOn": "10-Jan-2023",
        "CourseOption": "NIL",
        "CourseDistribUtion": "DC"
      },
      {
        "Slno": "32",
        "CourseCode": "BFST106L",
        "CourseTitle": "Pattern Making and Garment Construction",
        "CourseType": "TH",
        "Credits": "2.0",
        "Grade": "E",
        "ExamMonth": "Nov-2022",
        "ResultDeclaredOn": "10-Jan-2023",
        "CourseOption": "NIL",
        "CourseDistribUtion": "DC"
      },
      {
        "Slno": "33",
        "CourseCode": "BFST106P",
        "CourseTitle": "Pattern Making and Garment Construction Lab",
        "CourseType": "LO",
        "Credits": "2.0",
        "Grade": "B",
        "ExamMonth": "L Nov-2022",
        "ResultDeclaredOn": "10-Jan-2023",
        "CourseOption": "NIL",
        "CourseDistribUtion": "DC"
      },
      {
        "Slno": "34",
        "CourseCode": "BFST201P",
        "CourseTitle": "Fashion Illustration",
        "CourseType": "LO",
        "Credits": "3.0",
        "Grade": "B",
        "ExamMonth": "Nov-2022",
        "ResultDeclaredOn": "10-Jan-2023",
        "CourseOption": "NIL",
        "CourseDistribUtion": "DLES"
      },
      {
        "Slno": "35",
        "CourseCode": "BMAT204L",
        "CourseTitle": "Solid Geometry and Linear Transformations",
        "CourseType": "TH",
        "Credits": "4.0",
        "Grade": "A B",
        "ExamMonth": "Nov-2022",
        "ResultDeclaredOn": "10-Jan-2023",
        "CourseOption": "NIL",
        "CourseDistribUtion": "FCBS M"
      },
      {
        "Slno": "36",
        "CourseCode": "BSTS201P",
        "CourseTitle": "Qualitative Skills Practice I",
        "CourseType": "SS",
        "Credits": "1.5",
        "Grade": "I B",
        "ExamMonth": "Nov-2022",
        "ResultDeclaredOn": "10-Jan-2023",
        "CourseOption": "NIL",
        "CourseDistribUtion": "FCHSS M"
      },
      {
        "Slno": "37",
        "CourseCode": "BFRE101L",
        "CourseTitle": "French I",
        "CourseType": "TH",
        "Credits": "2.0",
        "Grade": "C",
        "ExamMonth": "Apr-2023",
        "ResultDeclaredOn": "24-May-2023",
        "CourseOption": "NIL",
        "CourseDistribUtion": "FCHSS M"
      },
      {
        "Slno": "38",
        "CourseCode": "BFST202L",
        "CourseTitle": "Yarn Manufacturing",
        "CourseType": "TH",
        "Credits": "C 3.0",
        "Grade": "C",
        "ExamMonth": "Apr-2023",
        "ResultDeclaredOn": "24-May-2023",
        "CourseOption": "NIL",
        "CourseDistribUtion": "DC"
      },
      {
        "Slno": "39",
        "CourseCode": "BFST202P",
        "CourseTitle": "Yarn Manufacturing Lab",
        "CourseType": "LO",
        "Credits": "1.0",
        "Grade": "B",
        "ExamMonth": "Apr-2023",
        "ResultDeclaredOn": "13-May-2023",
        "CourseOption": "NIL",
        "CourseDistribUtion": "DC"
      },
      {
        "Slno": "40",
        "CourseCode": "BFST203P",
        "CourseTitle": "Kid’s and Men’s Wear",
        "CourseType": "LO",
        "Credits": "I 4.0",
        "Grade": "C",
        "ExamMonth": "Apr-2023",
        "ResultDeclaredOn": "13-May-2023",
        "CourseOption": "NIL",
        "CourseDistribUtion": "DC"
      },
      {
        "Slno": "41",
        "CourseCode": "BFST212L",
        "CourseTitle": "Fashion Communication",
        "CourseType": "TH",
        "Credits": "3.0",
        "Grade": "E",
        "ExamMonth": "Apr-2023",
        "ResultDeclaredOn": "24-May-2023",
        "CourseOption": "NIL",
        "CourseDistribUtion": "DE"
      },
      {
        "Slno": "42",
        "CourseCode": "BFST304E",
        "CourseTitle": "Accessories Designing and Manufacturing",
        "CourseType": "ETL",
        "Credits": "F 3.0",
        "Grade": "C",
        "ExamMonth": "Apr-2023",
        "ResultDeclaredOn": "24-May-2023",
        "CourseOption": "NIL",
        "CourseDistribUtion": "DE"
      },
      {
        "Slno": "43",
        "CourseCode": "BHUM107L",
        "CourseTitle": "SUSTAINABILITY AND SOCIETY",
        "CourseType": "F TH",
        "Credits": "3.0",
        "Grade": "D",
        "ExamMonth": "Apr-2023",
        "ResultDeclaredOn": "24-May-2023",
        "CourseOption": "NIL",
        "CourseDistribUtion": "FCHSS M"
      },
      {
        "Slno": "44",
        "CourseCode": "BMAT202L",
        "CourseTitle": "Probability and Statistics",
        "CourseType": "TH",
        "Credits": "3.0",
        "Grade": "B",
        "ExamMonth": "Apr-2023",
        "ResultDeclaredOn": "24-May-2023",
        "CourseOption": "NIL",
        "CourseDistribUtion": "FCBS M"
      },
      {
        "Slno": "45",
        "CourseCode": "BMAT202P",
        "CourseTitle": "O Probability and Statistics Lab",
        "CourseType": "LO",
        "Credits": "1.0",
        "Grade": "B",
        "ExamMonth": "Apr-2023",
        "ResultDeclaredOn": "13-May-2023",
        "CourseOption": "NIL",
        "CourseDistribUtion": "FCBS M"
      },
      {
        "Slno": "46",
        "CourseCode": "BSTS202P",
        "CourseTitle": "N Qualitative Skills Practice II",
        "CourseType": "SS",
        "Credits": "1.5",
        "Grade": "C",
        "ExamMonth": "Apr-2023",
        "ResultDeclaredOn": "13-May-2023",
        "CourseOption": "NIL",
        "CourseDistribUtion": "FCHSS M"
      },
      {
        "Slno": "47",
        "CourseCode": "BFST105L",
        "CourseTitle": "Couture Techniques",
        "CourseType": "TH",
        "Credits": "3.0",
        "Grade": "E",
        "ExamMonth": "Aug-2023",
        "ResultDeclaredOn": "26-Aug-2023",
        "CourseOption": "NIL",
        "CourseDistribUtion": "DC"
      },
      {
        "Slno": "48",
        "CourseCode": "BFST105P",
        "CourseTitle": "Couture Techniques Lab",
        "CourseType": "LO",
        "Credits": "1.0",
        "Grade": "B",
        "ExamMonth": "Aug-2023",
        "ResultDeclaredOn": "26-Aug-2023",
        "CourseOption": "NIL",
        "CourseDistribUtion": "DC"
      },
      {
        "Slno": "49",
        "CourseCode": "BFST107L",
        "CourseTitle": "U Apparel Merchandising and Costing",
        "CourseType": "TH",
        "Credits": "4.0",
        "Grade": "B",
        "ExamMonth": "Aug-2023",
        "ResultDeclaredOn": "26-Aug-2023",
        "CourseOption": "NIL",
        "CourseDistribUtion": "DC"
      },
      {
        "Slno": "50",
        "CourseCode": "BFST204P",
        "CourseTitle": "Women’s Wear and Lingerie",
        "CourseType": "LO",
        "Credits": "3.0",
        "Grade": "B",
        "ExamMonth": "Aug-2023",
        "ResultDeclaredOn": "26-Aug-2023",
        "CourseOption": "NIL",
        "CourseDistribUtion": "DC"
      },
      {
        "Slno": "51",
        "CourseCode": "BFST301L",
        "CourseTitle": "Fabric Manufacturing",
        "CourseType": "TH",
        "Credits": "3.0",
        "Grade": "C",
        "ExamMonth": "Aug-2023",
        "ResultDeclaredOn": "26-Aug-2023",
        "CourseOption": "NIL",
        "CourseDistribUtion": "DC"
      },
      {
        "Slno": "52",
        "CourseCode": "BFST301P",
        "CourseTitle": "Fabric Manufacturing Lab",
        "CourseType": "LO",
        "Credits": "1.0",
        "Grade": "C",
        "ExamMonth": "Aug-2023",
        "ResultDeclaredOn": "26-Aug-2023",
        "CourseOption": "NIL",
        "CourseDistribUtion": "DC"
      },
      {
        "Slno": "53",
        "CourseCode": "BFST302P",
        "CourseTitle": "Digital Fashion and Apparel Design Lab",
        "CourseType": "LO",
        "Credits": "3.0",
        "Grade": "A",
        "ExamMonth": "Aug-2023",
        "ResultDeclaredOn": "26-Aug-2023",
        "CourseOption": "NIL",
        "CourseDistribUtion": "DC"
      },
      {
        "Slno": "54",
        "CourseCode": "BSTS301P",
        "CourseTitle": "Advanced Competitive Coding - I",
        "CourseType": "SS",
        "Credits": "1.5",
        "Grade": "E",
        "ExamMonth": "Aug-2023",
        "ResultDeclaredOn": "26-Aug-2023",
        "CourseOption": "NIL",
        "CourseDistribUtion": "OE"
      },
      {
        "Slno": "55",
        "CourseCode": "BSSC101N",
        "CourseTitle": "Essence of Traditional Knowledge",
        "CourseType": "OC",
        "Credits": "2.0",
        "Grade": "P",
        "ExamMonth": "Jan-2024",
        "ResultDeclaredOn": "02-Apr-2024",
        "CourseOption": "NCG",
        "CourseDistribUtion": "NGCR"
      },
      {
        "Slno": "56",
        "CourseCode": "BSSC102N",
        "CourseTitle": "Indian Constitution",
        "CourseType": "OC",
        "Credits": "2.0",
        "Grade": "P",
        "ExamMonth": "Jan-2024",
        "ResultDeclaredOn": "02-Apr-2024",
        "CourseOption": "NCG",
        "CourseDistribUtion": "NGCR"
      },
      {
        "Slno": "57",
        "CourseCode": "AEXC150N",
        "CourseTitle": "Malayalam Arts and Literature",
        "CourseType": "ECA",
        "Credits": "2.0",
        "Grade": "P",
        "ExamMonth": "May-2024",
        "ResultDeclaredOn": "07-Jun-2024",
        "CourseOption": "NCPF",
        "CourseDistribUtion": "NGCR"
      },
      {
        "Slno": "58",
        "CourseCode": "BFST210E",
        "CourseTitle": "Visual Merchandising",
        "CourseType": "ETL",
        "Credits": "3.0",
        "Grade": "E",
        "ExamMonth": "May-2024",
        "ResultDeclaredOn": "12-Jun-2024",
        "CourseOption": "NIL",
        "CourseDistribUtion": "DE"
      },
      {
        "Slno": "59",
        "CourseCode": "BFST307L",
        "CourseTitle": "Denim Technology",
        "CourseType": "TH",
        "Credits": "3.0",
        "Grade": "D",
        "ExamMonth": "May-2024",
        "ResultDeclaredOn": "24-Jun-2024",
        "CourseOption": "NIL",
        "CourseDistribUtion": "DE"
      },
      {
        "Slno": "60",
        "CourseCode": "BFST399J",
        "CourseTitle": "Summer Industrial Internship",
        "CourseType": "PJT",
        "Credits": "1.0",
        "Grade": "B",
        "ExamMonth": "May-2024",
        "ResultDeclaredOn": "28-May-2024",
        "CourseOption": "NIL",
        "CourseDistribUtion": "PI"
      },
      {
        "Slno": "61",
        "CourseCode": "BFST401L",
        "CourseTitle": "Textile Processing and Finishing",
        "CourseType": "TH",
        "Credits": "3.0",
        "Grade": "E",
        "ExamMonth": "May-2024",
        "ResultDeclaredOn": "24-Jun-2024",
        "CourseOption": "NIL",
        "CourseDistribUtion": "DC"
      },
      {
        "Slno": "62",
        "CourseCode": "BFST401P",
        "CourseTitle": "Textile Processing and Finishing Lab",
        "CourseType": "LO",
        "Credits": "1.0",
        "Grade": "C",
        "ExamMonth": "May-2024",
        "ResultDeclaredOn": "28-May-2024",
        "CourseOption": "NIL",
        "CourseDistribUtion": "DC"
      },
      {
        "Slno": "63",
        "CourseCode": "BFST402L",
        "CourseTitle": "Fabric Structure and Design Analysis",
        "CourseType": "TH",
        "Credits": "3.0",
        "Grade": "N1",
        "ExamMonth": "L May-2024",
        "ResultDeclaredOn": "24-Jun-2024",
        "CourseOption": "NIL",
        "CourseDistribUtion": "DC"
      },
      {
        "Slno": "64",
        "CourseCode": "BFST402L",
        "CourseTitle": "Fabric Structure and Design Analysis",
        "CourseType": "TH",
        "Credits": "3.0",
        "Grade": "A D",
        "ExamMonth": "Apr-2025",
        "ResultDeclaredOn": "02-Jun-2025",
        "CourseOption": "NIL",
        "CourseDistribUtion": "DC"
      },
      {
        "Slno": "65",
        "CourseCode": "BFST402P",
        "CourseTitle": "Fabric Structure and Design Analysis Lab",
        "CourseType": "LO",
        "Credits": "1.0",
        "Grade": "N1",
        "ExamMonth": "May-2024",
        "ResultDeclaredOn": "28-May-2024",
        "CourseOption": "NIL",
        "CourseDistribUtion": "DC"
      },
      {
        "Slno": "66",
        "CourseCode": "BFST402P",
        "CourseTitle": "Fabric Structure and Design Analysis Lab",
        "CourseType": "LO",
        "Credits": "1.0",
        "Grade": "I B",
        "ExamMonth": "Apr-2025",
        "ResultDeclaredOn": "20-May-2025",
        "CourseOption": "NIL",
        "CourseDistribUtion": "DC"
      },
      {
        "Slno": "67",
        "CourseCode": "BFST403P",
        "CourseTitle": "Computer Aided Garment Design Lab",
        "CourseType": "LO",
        "Credits": "C 3.0",
        "Grade": "C",
        "ExamMonth": "May-2024",
        "ResultDeclaredOn": "28-May-2024",
        "CourseOption": "NIL",
        "CourseDistribUtion": "DC"
      },
      {
        "Slno": "68",
        "CourseCode": "BHUM222L",
        "CourseTitle": "Security Analysis and Portfolio Management",
        "CourseType": "TH",
        "Credits": "I 3.0",
        "Grade": "D",
        "ExamMonth": "May-2024",
        "ResultDeclaredOn": "12-Jun-2024",
        "CourseOption": "NIL",
        "CourseDistribUtion": "OE"
      },
      {
        "Slno": "69",
        "CourseCode": "BSTS302P",
        "CourseTitle": "Advanced Competitive Coding - II",
        "CourseType": "SS",
        "Credits": "F 1.5",
        "Grade": "E",
        "ExamMonth": "May-2024",
        "ResultDeclaredOn": "01-Jun-2024",
        "CourseOption": "NIL",
        "CourseDistribUtion": "OE"
      },
      {
        "Slno": "70",
        "CourseCode": "BCLE214L",
        "CourseTitle": "Global Warming",
        "CourseType": "TH",
        "Credits": "3.0",
        "Grade": "D",
        "ExamMonth": "Dec-2024",
        "ResultDeclaredOn": "04-Jan-2025",
        "CourseOption": "NIL",
        "CourseDistribUtion": "FCHSS M"
      },
      {
        "Slno": "71",
        "CourseCode": "BFST211L",
        "CourseTitle": "Fashion Merchandising and Marketing",
        "CourseType": "F TH",
        "Credits": "3.0",
        "Grade": "D",
        "ExamMonth": "Dec-2024",
        "ResultDeclaredOn": "04-Jan-2025",
        "CourseOption": "NIL",
        "CourseDistribUtion": "DE"
      },
      {
        "Slno": "72",
        "CourseCode": "BFST405P",
        "CourseTitle": "Fashion Design Portfolio",
        "CourseType": "LO",
        "Credits": "3.0",
        "Grade": "N1",
        "ExamMonth": "Dec-2024",
        "ResultDeclaredOn": "03-Jan-2025",
        "CourseOption": "NIL",
        "CourseDistribUtion": "DC"
      },
      {
        "Slno": "73",
        "CourseCode": "BFST405P",
        "CourseTitle": "O Fashion Design Portfolio",
        "CourseType": "LO",
        "Credits": "3.0",
        "Grade": "E",
        "ExamMonth": "May-2025",
        "ResultDeclaredOn": "23-Jun-2025",
        "CourseOption": "NIL",
        "CourseDistribUtion": "DC"
      },
      {
        "Slno": "74",
        "CourseCode": "BFST497J",
        "CourseTitle": "Project - I",
        "CourseType": "PJT",
        "Credits": "3.0",
        "Grade": "F",
        "ExamMonth": "Dec-2024",
        "ResultDeclaredOn": "06-Jan-2025",
        "CourseOption": "NIL",
        "CourseDistribUtion": "PI"
      },
      {
        "Slno": "75",
        "CourseCode": "BFST497J",
        "CourseTitle": "Project - I",
        "CourseType": "PJT",
        "Credits": "3.0",
        "Grade": "C",
        "ExamMonth": "Apr-2025",
        "ResultDeclaredOn": "12-May-2025",
        "CourseOption": "NIL",
        "CourseDistribUtion": "PI"
      },
      {
        "Slno": "76",
        "CourseCode": "BHUM103L",
        "CourseTitle": "N Micro Economics",
        "CourseType": "TH",
        "Credits": "3.0",
        "Grade": "N1",
        "ExamMonth": "Dec-2024",
        "ResultDeclaredOn": "04-Jan-2025",
        "CourseOption": "NIL",
        "CourseDistribUtion": "FCHSS M"
      },
      {
        "Slno": "77",
        "CourseCode": "BHUM103L",
        "CourseTitle": "Micro Economics",
        "CourseType": "TH",
        "Credits": "3.0",
        "Grade": "E",
        "ExamMonth": "May-2025",
        "ResultDeclaredOn": "23-Jun-2025",
        "CourseOption": "NIL",
        "CourseDistribUtion": "FCHSS M"
      },
      {
        "Slno": "78",
        "CourseCode": "CFOC575M",
        "CourseTitle": "U Wildlife Ecology",
        "CourseType": "OC",
        "Credits": "3.0",
        "Grade": "S",
        "ExamMonth": "Dec-2024",
        "ResultDeclaredOn": "03-Jan-2025",
        "CourseOption": "NIL",
        "CourseDistribUtion": "OE"
      },
      {
        "Slno": "79",
        "CourseCode": "BFST498J",
        "CourseTitle": "Project - II / Internship",
        "CourseType": "PJT",
        "Credits": "5.0",
        "Grade": "C",
        "ExamMonth": "Apr-2025",
        "ResultDeclaredOn": "12-May-2025",
        "CourseOption": "NIL",
        "CourseDistribUtion": "PI"
      }
    ],
    "curriculum_details": [
      {
        "CurriculumDistributionType": "Foundation Core - Basic Sciences and Mathematics",
        "CreditsRequired": "24.0",
        "CreditsEarned": "24.0"
      },
      {
        "CurriculumDistributionType": "Foundation Core - Basic Engineering Sciences",
        "CreditsRequired": "15.0",
        "CreditsEarned": "15.0"
      },
      {
        "CurriculumDistributionType": "Foundation Core - Humanities, Social Sciences and Management",
        "CreditsRequired": "15.0",
        "CreditsEarned": "15.0"
      }
    ],
    "curriculum_details_1": [
      {
        "DisciplinelinkedEngineeringSciences": "Discipline Core",
        "110": "47.0"
      },
      {
        "DisciplinelinkedEngineeringSciences": "Discipline Elective",
        "110": "15.0"
      },
      {
        "DisciplinelinkedEngineeringSciences": "Projects and Internship",
        "110": "9.0"
      },
      {
        "DisciplinelinkedEngineeringSciences": "Open Elective",
        "110": "15.0"
      },
      {
        "DisciplinelinkedEngineeringSciences": "Non-graded Core Requirement",
        "110": "11.0"
      },
      {
        "DisciplinelinkedEngineeringSciences": "Bridge Course",
        "110": "2.0"
      },
      {
        "DisciplinelinkedEngineeringSciences": "Multidisciplinary Electives",
        "110": "0.0"
      },
      {
        "DisciplinelinkedEngineeringSciences": "Total Credits",
        "110": "164.0"
      }
    ],
    "i_basket_details": [
      {
        "BasketTitle": "Foreign Language",
        "DistributionType": "C FCHSSM",
        "CreditsRequired": "2.0",
        "CreditsEarned": "2.0"
      },
      {
        "BasketTitle": "Extra curricular activities",
        "DistributionType": "NGCR",
        "CreditsRequired": "2.0",
        "CreditsEarned": "2.0"
      },
      {
        "BasketTitle": "HSM Elective",
        "DistributionType": "I FCHSSM",
        "CreditsRequired": "3.0",
        "CreditsEarned": "3.0"
      }
    ],
    "f_cgpa_details": [
      {
        "CreditsRegistered": "153.0",
        "CreditsEarned": "153.0",
        "Cgpa": "6.88",
        "SGrades": "1",
        "AGrades": "F 5",
        "BGrades": "20",
        "CGrades": "17",
        "DGrades": "10",
        "EGrades": "12",
        "FGrades": "0",
        "NGrades": "0"
      }
    ]
  }
}