{
  "student_information": {
    "register_number": "20MBA1048",
    "name": "SURIYABALAJI"
  },
  "tables": {
    "grade_history": [
      {
        "Slno": "1",
        "CourseCode": "BMT5118",
        "CourseTitle": "Operations Management",
        "CourseType": "TH",
        "Credits": "3.0",
        "Grade": "N3",
        "ExamMonth": "Jan-2021",
        "ResultDeclaredOn": "15-Mar-2021",
        "CourseOption": "NIL",
        "CourseDistribUtion": "PC"
      },
      {
        "Slno": "2",
        "CourseCode": "BMT5119",
        "CourseTitle": "Marketing Management - Fundamentals",
        "CourseType": "TH",
        "Credits": "3.0",
        "Grade": "N2",
        "ExamMonth": "Jan-2021",
        "ResultDeclaredOn": "15-Mar-2021",
        "CourseOption": "NIL",
        "CourseDistribUtion": "PC"
      },
      {
        "Slno": "3",
        "CourseCode": "BMT5120",
        "CourseTitle": "Human Resource Management",
        "CourseType": "TH",
        "Credits": "3.0",
        "Grade": "N3",
        "ExamMonth": "Jan-2021",
        "ResultDeclaredOn": "15-Mar-2021",
        "CourseOption": "NIL",
        "CourseDistribUtion": "PC"
      },
      {
        "Slno": "4",
        "CourseCode": "BMT5121",
        "CourseTitle": "Corporate Governance and Ethics",
        "CourseType": "TH",
        "Credits": "1.0",
        "Grade": "N2",
        "ExamMonth": "L Jan-2021",
        "ResultDeclaredOn": "15-Mar-2021",
        "CourseOption": "NIL",
        "CourseDistribUtion": "PC"
      },
      {
        "Slno": "5",
        "CourseCode": "BMT6111",
        "CourseTitle": "Macro Economics",
        "CourseType": "TH",
        "Credits": "2.0",
        "Grade": "N3",
        "ExamMonth": "Jan-2021",
        "ResultDeclaredOn": "15-Mar-2021",
        "CourseOption": "NIL",
        "CourseDistribUtion": "PC"
      },
      {
        "Slno": "6",
        "CourseCode": "BMT6112",
        "CourseTitle": "Basic Financial Management",
        "CourseType": "TH",
        "Credits": "2.0",
        "Grade": "A N3",
        "ExamMonth": "Jan-2021",
        "ResultDeclaredOn": "15-Mar-2021",
        "CourseOption": "NIL",
        "CourseDistribUtion": "PC"
      },
      {
        "Slno": "7",
        "CourseCode": "BMT6113",
        "CourseTitle": "Business Research Methods",
        "CourseType": "ETP",
        "Credits": "3.0",
        "Grade": "I N",
        "ExamMonth": "Jan-2021",
        "ResultDeclaredOn": "15-Mar-2021",
        "CourseOption": "NIL",
        "CourseDistribUtion": "PC"
      },
      {
        "Slno": "8",
        "CourseCode": "STS5001",
        "CourseTitle": "Essentials of Business Etiquettes",
        "CourseType": "SS",
        "Credits": "1.0",
        "Grade": "N3",
        "ExamMonth": "Jan-2021",
        "ResultDeclaredOn": "15-Mar-2021",
        "CourseOption": "NIL",
        "CourseDistribUtion": "PC"
      }
    ],
    "cgpa_details": [
      {
        "CreditsRegistered": "18.0",
        "CreditsEarned": "0.0",
        "Cgpa": "0.00",
        "NSGrades": "0",
        "AGrades": "0",
        "BGrades": "0",
        "CGrades": "0",
        "DGrades": "0",
        "EGrades": "0",
        "FGrades": "0",
        "NGrades": "8"
      }
    ]
  }
}