{
  "student_information": {
    "register_number": "14BCE1120",
    "name": "KALIAPPAN BUBATHY KARTHY"
  },
  "tables": {
    "grade_history_combined": [
      {
        "Slno": "1",
        "CourseCode": "CSE205",
        "CourseTitle": "Computer Architecture and Organization",
        "CourseType": "Theory",
        "Credits": "4.0",
        "Grade": "N",
        "ExamMonth": "Apr-2018",
        "ResultDeclaredOn": "09-May-2018",
        "CourseOption": "NIL"
      },
      {
        "Slno": "2",
        "CourseCode": "CSE205",
        "CourseTitle": "Computer Architecture and Organization",
        "CourseType": "Theory",
        "Credits": "4.0",
        "Grade": "N",
        "ExamMonth": "Nov-2015",
        "ResultDeclaredOn": "23-Dec-2015",
        "CourseOption": "NIL"
      },
      {
        "Slno": "3",
        "CourseCode": "CSE323",
        "CourseTitle": "Computer Networks",
        "CourseType": "TheoryLab",
        "Credits": "4.0",
        "Grade": "N",
        "ExamMonth": "Apr-2018",
        "ResultDeclaredOn": "09-May-2018",
        "CourseOption": "NIL"
      },
      {
        "Slno": "4",
        "CourseCode": "CSE327",
        "CourseTitle": "Image and Vision Computing",
        "CourseType": "Theory",
        "Credits": "3.0",
        "Grade": "N",
        "ExamMonth": "Apr-2018",
        "ResultDeclaredOn": "09-May-2018",
        "CourseOption": "NIL"
      },
      {
        "Slno": "5",
        "CourseCode": "EEE101",
        "CourseTitle": "Basic Electrical and Electronics Engineering",
        "CourseType": "TheoryLab",
        "Credits": "4.0",
        "Grade": "E",
        "ExamMonth": "Apr-2018",
        "ResultDeclaredOn": "09-May-2018",
        "CourseOption": "NIL"
      },
      {
        "Slno": "6",
        "CourseCode": "EEE101",
        "CourseTitle": "Basic Electrical and Electronics Engineering",
        "CourseType": "TheoryLab",
        "Credits": "4.0",
        "Grade": "N",
        "ExamMonth": "Jul-2016",
        "ResultDeclaredOn": "22-Jul-2016",
        "CourseOption": "NIL"
      },
      {
        "Slno": "7",
        "CourseCode": "EEE101",
        "CourseTitle": "Basic Electrical and Electronics Engineering",
        "CourseType": "TheoryLab",
        "Credits": "4.0",
        "Grade": "F",
        "ExamMonth": "Nov-2014",
        "ResultDeclaredOn": "15-Dec-2014",
        "CourseOption": "NIL"
      },
      {
        "Slno": "8",
        "CourseCode": "EEE101",
        "CourseTitle": "Basic Electrical and Electronics Engineering",
        "CourseType": "TheoryLab",
        "Credits": "4.0",
        "Grade": "N",
        "ExamMonth": "Nov-2017",
        "ResultDeclaredOn": "20-Dec-2017",
        "CourseOption": "NIL"
      },
      {
        "Slno": "9",
        "CourseCode": "EEE103",
        "CourseTitle": "Electronics",
        "CourseType": "TheoryLab",
        "Credits": "4.0",
        "Grade": "D",
        "ExamMonth": "Apr-2018",
        "ResultDeclaredOn": "09-May-2018",
        "CourseOption": "NIL"
      },
      {
        "Slno": "10",
        "CourseCode": "EEE103",
        "CourseTitle": "Electronics",
        "CourseType": "TheoryLab",
        "Credits": "4.0",
        "Grade": "F",
        "ExamMonth": "Nov-2015",
        "ResultDeclaredOn": "23-Dec-2015",
        "CourseOption": "NIL"
      },
      {
        "Slno": "11",
        "CourseCode": "HUM121",
        "CourseTitle": "Ethics and Values",
        "CourseType": "TheoryLab",
        "Credits": "3.0",
        "Grade": "E",
        "ExamMonth": "Apr-2018",
        "ResultDeclaredOn": "09-May-2018",
        "CourseOption": "NIL"
      },
      {
        "Slno": "12",
        "CourseCode": "HUM121",
        "CourseTitle": "Ethics and Values",
        "CourseType": "TheoryLab",
        "Credits": "3.0",
        "Grade": "N",
        "ExamMonth": "Nov-2015",
        "ResultDeclaredOn": "13-Jan-2016",
        "CourseOption": "NIL"
      },
      {
        "Slno": "13",
        "CourseCode": "CHY101",
        "CourseTitle": "Engineering Chemistry",
        "CourseType": "TheoryLab",
        "Credits": "4.0",
        "Grade": "D",
        "ExamMonth": "May-2015",
        "ResultDeclaredOn": "16-Jun-2015",
        "CourseOption": "NIL"
      },
      {
        "Slno": "14",
        "CourseCode": "CSE109",
        "CourseTitle": "Digital Logic",
        "CourseType": "TheoryLab",
        "Credits": "4.0",
        "Grade": "F",
        "ExamMonth": "May-2015",
        "ResultDeclaredOn": "16-Jun-2015",
        "CourseOption": "NIL"
      },
      {
        "Slno": "15",
        "CourseCode": "CSE109",
        "CourseTitle": "Digital Logic",
        "CourseType": "TheoryLab",
        "Credits": "4.0",
        "Grade": "C",
        "ExamMonth": "May-2017",
        "ResultDeclaredOn": "16-Jun-2017",
        "CourseOption": "NIL"
      },
      {
        "Slno": "16",
        "CourseCode": "CSE109",
        "CourseTitle": "Digital Logic",
        "CourseType": "TheoryLab",
        "Credits": "4.0",
        "Grade": "F",
        "ExamMonth": "Jun-2016",
        "ResultDeclaredOn": "20-Jun-2016",
        "CourseOption": "NIL"
      },
      {
        "Slno": "17",
        "CourseCode": "CSE219",
        "CourseTitle": "Object Oriented Paradigm and Programming",
        "CourseType": "TheoryLab",
        "Credits": "5.0",
        "Grade": "F",
        "ExamMonth": "May-2015",
        "ResultDeclaredOn": "16-Jun-2015",
        "CourseOption": "NIL"
      },
      {
        "Slno": "18",
        "CourseCode": "CSE219",
        "CourseTitle": "Object Oriented Paradigm and Programming",
        "CourseType": "TheoryLab",
        "Credits": "5.0",
        "Grade": "F",
        "ExamMonth": "Jun-2016",
        "ResultDeclaredOn": "20-Jun-2016",
        "CourseOption": "NIL"
      },
      {
        "Slno": "19",
        "CourseCode": "CSE219",
        "CourseTitle": "Object Oriented Paradigm and Programming",
        "CourseType": "ETL",
        "Credits": "5.0",
        "Grade": "B",
        "ExamMonth": "Jul-2020",
        "ResultDeclaredOn": "15-Jul-2020",
        "CourseOption": "NIL"
      },
      {
        "Slno": "20",
        "CourseCode": "ENG102",
        "CourseTitle": "English for Engineers - II",
        "CourseType": "TheoryLab",
        "Credits": "3.0",
        "Grade": "E",
        "ExamMonth": "May-2015",
        "ResultDeclaredOn": "16-Jun-2015",
        "CourseOption": "NIL"
      },
      {
        "Slno": "21",
        "CourseCode": "MAT106",
        "CourseTitle": "Discrete Mathematical Structures",
        "CourseType": "Theory",
        "Credits": "4.0",
        "Grade": "F",
        "ExamMonth": "May-2015",
        "ResultDeclaredOn": "16-Jun-2015",
        "CourseOption": "NIL"
      },
      {
        "Slno": "22",
        "CourseCode": "MAT106",
        "CourseTitle": "Discrete Mathematical Structures",
        "CourseType": "Theory",
        "Credits": "4.0",
        "Grade": "F",
        "ExamMonth": "Jun-2016",
        "ResultDeclaredOn": "20-Jun-2016",
        "CourseOption": "NIL"
      },
      {
        "Slno": "23",
        "CourseCode": "MAT106",
        "CourseTitle": "Discrete Mathematical Structures",
        "CourseType": "Theory",
        "Credits": "4.0",
        "Grade": "D",
        "ExamMonth": "Jul-2017",
        "ResultDeclaredOn": "18-Jul-2017",
        "CourseOption": "NIL"
      },
      {
        "Slno": "24",
        "CourseCode": "MAT115",
        "CourseTitle": "Differential and Difference Equations",
        "CourseType": "TheoryLab",
        "Credits": "4.0",
        "Grade": "F",
        "ExamMonth": "May-2015",
        "ResultDeclaredOn": "16-Jun-2015",
        "CourseOption": "NIL"
      },
      {
        "Slno": "25",
        "CourseCode": "MAT115",
        "CourseTitle": "Differential and Difference Equations",
        "CourseType": "TheoryLab",
        "Credits": "4.0",
        "Grade": "F",
        "ExamMonth": "Jun-2016",
        "ResultDeclaredOn": "20-Jun-2016",
        "CourseOption": "NIL"
      },
      {
        "Slno": "26",
        "CourseCode": "MEE102",
        "CourseTitle": "Workshop Practice",
        "CourseType": "Lab",
        "Credits": "1.0",
        "Grade": "A",
        "ExamMonth": "May-2015",
        "ResultDeclaredOn": "16-Jun-2015",
        "CourseOption": "NIL"
      },
      {
        "Slno": "27",
        "CourseCode": "CSE222",
        "CourseTitle": "Operating Systems",
        "CourseType": "TheoryLab",
        "Credits": "4.0",
        "Grade": "N",
        "ExamMonth": "May-2016",
        "ResultDeclaredOn": "10-Jun-2016",
        "CourseOption": "NIL"
      },
      {
        "Slno": "28",
        "CourseCode": "CSE222",
        "CourseTitle": "Operating Systems",
        "CourseType": "TheoryLab",
        "Credits": "4.0",
        "Grade": "C",
        "ExamMonth": "Nov-2017",
        "ResultDeclaredOn": "20-Dec-2017",
        "CourseOption": "NIL"
      },
      {
        "Slno": "29",
        "CourseCode": "FRE101",
        "CourseTitle": "Basic French",
        "CourseType": "Theory",
        "Credits": "2.0",
        "Grade": "E",
        "ExamMonth": "May-2016",
        "ResultDeclaredOn": "10-Jun-2016",
        "CourseOption": "NIL"
      },
      {
        "Slno": "30",
        "CourseCode": "FRE101",
        "CourseTitle": "Basic French",
        "CourseType": "Theory",
        "Credits": "2.0",
        "Grade": "F",
        "ExamMonth": "Nov-2014",
        "ResultDeclaredOn": "15-Dec-2014",
        "CourseOption": "NIL"
      },
      {
        "Slno": "31",
        "CourseCode": "MAT202",
        "CourseTitle": "Linear Algebra",
        "CourseType": "Theory",
        "Credits": "4.0",
        "Grade": "N",
        "ExamMonth": "May-2016",
        "ResultDeclaredOn": "10-Jun-2016",
        "CourseOption": "NIL"
      },
      {
        "Slno": "32",
        "CourseCode": "MAT207",
        "CourseTitle": "Applied Probability, Statistics and Reliability",
        "CourseType": "Theory",
        "Credits": "4.0",
        "Grade": "F",
        "ExamMonth": "May-2016",
        "ResultDeclaredOn": "10-Jun-2016",
        "CourseOption": "NIL"
      },
      {
        "Slno": "33",
        "CourseCode": "MAT207",
        "CourseTitle": "Applied Probability, Statistics and Reliability",
        "CourseType": "Theory",
        "Credits": "4.0",
        "Grade": "W",
        "ExamMonth": "May-2018",
        "ResultDeclaredOn": "17-May-2018",
        "CourseOption": "NIL"
      },
      {
        "Slno": "34",
        "CourseCode": "MAT207",
        "CourseTitle": "Applied Probability, Statistics and Reliability",
        "CourseType": "Theory",
        "Credits": "4.0",
        "Grade": "F",
        "ExamMonth": "Jul-2017",
        "ResultDeclaredOn": "18-Jul-2017",
        "CourseOption": "NIL"
      },
      {
        "Slno": "35",
        "CourseCode": "MAT207",
        "CourseTitle": "Applied Probability, Statistics and Reliability",
        "CourseType": "Theory",
        "Credits": "4.0",
        "Grade": "F",
        "ExamMonth": "Dec-2016",
        "ResultDeclaredOn": "07-Feb-2017",
        "CourseOption": "NIL"
      },
      {
        "Slno": "36",
        "CourseCode": "STS202",
        "CourseTitle": "Soft Skills",
        "CourseType": "SS",
        "Credits": "1.0",
        "Grade": "B",
        "ExamMonth": "May-2016",
        "ResultDeclaredOn": "28-Jun-2016",
        "CourseOption": "NIL"
      },
      {
        "Slno": "37",
        "CourseCode": "CSE320",
        "CourseTitle": "Multicore Systems Programming",
        "CourseType": "Theory",
        "Credits": "3.0",
        "Grade": "E",
        "ExamMonth": "May-2017",
        "ResultDeclaredOn": "16-Jun-2017",
        "CourseOption": "NIL"
      },
      {
        "Slno": "38",
        "CourseCode": "ECE104",
        "CourseTitle": "Discrete Time Systems and Processing",
        "CourseType": "Theory",
        "Credits": "3.0",
        "Grade": "F",
        "ExamMonth": "May-2017",
        "ResultDeclaredOn": "16-Jun-2017",
        "CourseOption": "NIL"
      },
      {
        "Slno": "39",
        "CourseCode": "ECE104",
        "CourseTitle": "Discrete Time Systems and Processing",
        "CourseType": "Theory",
        "Credits": "3.0",
        "Grade": "W",
        "ExamMonth": "May-2018",
        "ResultDeclaredOn": "17-May-2018",
        "CourseOption": "NIL"
      },
      {
        "Slno": "40",
        "CourseCode": "MAT206",
        "CourseTitle": "Graph Theory and its Applications",
        "CourseType": "Theory",
        "Credits": "4.0",
        "Grade": "F",
        "ExamMonth": "May-2017",
        "ResultDeclaredOn": "16-Jun-2017",
        "CourseOption": "NIL"
      },
      {
        "Slno": "41",
        "CourseCode": "MAT206",
        "CourseTitle": "Graph Theory and its Applications",
        "CourseType": "Theory",
        "Credits": "4.0",
        "Grade": "W",
        "ExamMonth": "May-2018",
        "ResultDeclaredOn": "17-May-2018",
        "CourseOption": "NIL"
      },
      {
        "Slno": "42",
        "CourseCode": "STS302",
        "CourseTitle": "Soft Skills",
        "CourseType": "SS",
        "Credits": "1.0",
        "Grade": "C",
        "ExamMonth": "May-2017",
        "ResultDeclaredOn": "14-Jun-2017",
        "CourseOption": "NIL"
      },
      {
        "Slno": "43",
        "CourseCode": "CSE309",
        "CourseTitle": "Programming Language Translators",
        "CourseType": "Theory",
        "Credits": "4.0",
        "Grade": "F",
        "ExamMonth": "May-2018",
        "ResultDeclaredOn": "17-May-2018",
        "CourseOption": "NIL"
      },
      {
        "Slno": "44",
        "CourseCode": "CSE309",
        "CourseTitle": "Programming Language Translators",
        "CourseType": "Theory",
        "Credits": "4.0",
        "Grade": "F",
        "ExamMonth": "Nov-2017",
        "ResultDeclaredOn": "19-Dec-2017",
        "CourseOption": "NIL"
      },
      {
        "Slno": "45",
        "CourseCode": "CSE324",
        "CourseTitle": "Database Systems",
        "CourseType": "TheoryLab",
        "Credits": "4.0",
        "Grade": "F",
        "ExamMonth": "May-2018",
        "ResultDeclaredOn": "17-May-2018",
        "CourseOption": "NIL"
      },
      {
        "Slno": "46",
        "CourseCode": "CSE324",
        "CourseTitle": "Database Systems",
        "CourseType": "ETL",
        "Credits": "4.0",
        "Grade": "F",
        "ExamMonth": "Jul-2020",
        "ResultDeclaredOn": "15-Jul-2020",
        "CourseOption": "NIL"
      },
      {
        "Slno": "47",
        "CourseCode": "CSE324",
        "CourseTitle": "Database Systems",
        "CourseType": "TheoryLab",
        "Credits": "4.0",
        "Grade": "N",
        "ExamMonth": "Aug-2019",
        "ResultDeclaredOn": "04-Sep-2019",
        "CourseOption": "NIL"
      },
      {
        "Slno": "48",
        "CourseCode": "CSE324",
        "CourseTitle": "Database Systems",
        "CourseType": "TheoryLab",
        "Credits": "4.0",
        "Grade": "N",
        "ExamMonth": "Nov-2016",
        "ResultDeclaredOn": "23-Dec-2016",
        "CourseOption": "NIL"
      },
      {
        "Slno": "49",
        "CourseCode": "CSE324",
        "CourseTitle": "Database Systems",
        "CourseType": "TheoryLab",
        "Credits": "4.0",
        "Grade": "F",
        "ExamMonth": "Nov-2017",
        "ResultDeclaredOn": "20-Dec-2017",
        "CourseOption": "NIL"
      },
      {
        "Slno": "50",
        "CourseCode": "CSE330",
        "CourseTitle": "Agent Based Intelligent Systems",
        "CourseType": "Theory",
        "Credits": "3.0",
        "Grade": "N",
        "ExamMonth": "May-2018",
        "ResultDeclaredOn": "07-Jun-2018",
        "CourseOption": "NIL"
      },
      {
        "Slno": "51",
        "CourseCode": "CSE330",
        "CourseTitle": "Agent Based Intelligent Systems",
        "CourseType": "Theory",
        "Credits": "3.0",
        "Grade": "N",
        "ExamMonth": "Nov-2016",
        "ResultDeclaredOn": "23-Dec-2016",
        "CourseOption": "NIL"
      },
      {
        "Slno": "52",
        "CourseCode": "MAT114",
        "CourseTitle": "Multivariable Calculus and Differential Equations",
        "CourseType": "ETL",
        "Credits": "4.0",
        "Grade": "F",
        "ExamMonth": "May-2018",
        "ResultDeclaredOn": "07-Jun-2018",
        "CourseOption": "NIL"
      },
      {
        "Slno": "53",
        "CourseCode": "MAT114",
        "CourseTitle": "Multivariable Calculus and Differential Equations",
        "CourseType": "TheoryLab",
        "Credits": "4.0",
        "Grade": "F",
        "ExamMonth": "Jun-2017",
        "ResultDeclaredOn": "05-Jul-2017",
        "CourseOption": "NIL"
      },
      {
        "Slno": "54",
        "CourseCode": "MAT114",
        "CourseTitle": "Multivariable Calculus and Differential Equations",
        "CourseType": "TheoryLab",
        "Credits": "4.0",
        "Grade": "N",
        "ExamMonth": "Jul-2016",
        "ResultDeclaredOn": "22-Jul-2016",
        "CourseOption": "NIL"
      },
      {
        "Slno": "55",
        "CourseCode": "MAT114",
        "CourseTitle": "Multivariable Calculus and Differential Equations",
        "CourseType": "TheoryLab",
        "Credits": "4.0",
        "Grade": "F",
        "ExamMonth": "Nov-2014",
        "ResultDeclaredOn": "15-Dec-2014",
        "CourseOption": "NIL"
      },
      {
        "Slno": "56",
        "CourseCode": "MEE437",
        "CourseTitle": "Operations Research",
        "CourseType": "TH",
        "Credits": "3.0",
        "Grade": "N",
        "ExamMonth": "May-2018",
        "ResultDeclaredOn": "07-Jun-2018",
        "CourseOption": "NIL"
      },
      {
        "Slno": "57",
        "CourseCode": "CSE208",
        "CourseTitle": "Theory of Computation",
        "CourseType": "Theory",
        "Credits": "4.0",
        "Grade": "F",
        "ExamMonth": "Jun-2017",
        "ResultDeclaredOn": "05-Jul-2017",
        "CourseOption": "NIL"
      },
      {
        "Slno": "58",
        "CourseCode": "CSE208",
        "CourseTitle": "Theory of Computation",
        "CourseType": "Theory",
        "Credits": "4.0",
        "Grade": "E",
        "ExamMonth": "Jul-2017",
        "ResultDeclaredOn": "18-Jul-2017",
        "CourseOption": "NIL"
      },
      {
        "Slno": "59",
        "CourseCode": "CSE208",
        "CourseTitle": "Theory of Computation",
        "CourseType": "Theory",
        "Credits": "4.0",
        "Grade": "F",
        "ExamMonth": "Nov-2015",
        "ResultDeclaredOn": "23-Dec-2015",
        "CourseOption": "NIL"
      },
      {
        "Slno": "60",
        "CourseCode": "CSE208",
        "CourseTitle": "Theory of Computation",
        "CourseType": "Theory",
        "Credits": "4.0",
        "Grade": "N",
        "ExamMonth": "Nov-2016",
        "ResultDeclaredOn": "23-Dec-2016",
        "CourseOption": "NIL"
      },
      {
        "Slno": "61",
        "CourseCode": "PHY101",
        "CourseTitle": "Modern Physics",
        "CourseType": "TheoryLab",
        "Credits": "4.0",
        "Grade": "E",
        "ExamMonth": "Jul-2016",
        "ResultDeclaredOn": "22-Jul-2016",
        "CourseOption": "NIL"
      },
      {
        "Slno": "62",
        "CourseCode": "PHY101",
        "CourseTitle": "Modern Physics",
        "CourseType": "TheoryLab",
        "Credits": "4.0",
        "Grade": "F",
        "ExamMonth": "Nov-2014",
        "ResultDeclaredOn": "15-Dec-2014",
        "CourseOption": "NIL"
      },
      {
        "Slno": "63",
        "CourseCode": "MAT203",
        "CourseTitle": "Numerical Analysis",
        "CourseType": "Theory",
        "Credits": "3.0",
        "Grade": "C",
        "ExamMonth": "Jul-2017",
        "ResultDeclaredOn": "18-Jul-2017",
        "CourseOption": "NIL"
      },
      {
        "Slno": "64",
        "CourseCode": "MAT203",
        "CourseTitle": "Numerical Analysis",
        "CourseType": "Theory",
        "Credits": "3.0",
        "Grade": "F",
        "ExamMonth": "Nov-2015",
        "ResultDeclaredOn": "23-Dec-2015",
        "CourseOption": "NIL"
      },
      {
        "Slno": "65",
        "CourseCode": "CSE202",
        "CourseTitle": "Algorithm Design and Analysis",
        "CourseType": "TH",
        "Credits": "4.0",
        "Grade": "E",
        "ExamMonth": "Jul-2018",
        "ResultDeclaredOn": "17-Jul-2018",
        "CourseOption": "NIL"
      },
      {
        "Slno": "66",
        "CourseCode": "CSE3006",
        "CourseTitle": "Embedded System Design",
        "CourseType": "ETP",
        "Credits": "4.0",
        "Grade": "N",
        "ExamMonth": "Jul-2018",
        "ResultDeclaredOn": "17-Jul-2018",
        "CourseOption": "NIL"
      },
      {
        "Slno": "67",
        "CourseCode": "CSE329",
        "CourseTitle": "Management Information Systems",
        "CourseType": "TH",
        "Credits": "3.0",
        "Grade": "E",
        "ExamMonth": "Jul-2018",
        "ResultDeclaredOn": "17-Jul-2018",
        "CourseOption": "NIL"
      },
      {
        "Slno": "68",
        "CourseCode": "CSE326",
        "CourseTitle": "Internet and Web Programming",
        "CourseType": "TheoryLab",
        "Credits": "4.0",
        "Grade": "N",
        "ExamMonth": "Aug-2019",
        "ResultDeclaredOn": "04-Sep-2019",
        "CourseOption": "NIL"
      },
      {
        "Slno": "69",
        "CourseCode": "CSE326",
        "CourseTitle": "Internet and Web Programming",
        "CourseType": "TheoryLab",
        "Credits": "4.0",
        "Grade": "N",
        "ExamMonth": "Nov-2017",
        "ResultDeclaredOn": "20-Dec-2017",
        "CourseOption": "NIL"
      },
      {
        "Slno": "70",
        "CourseCode": "CSE101",
        "CourseTitle": "Computer Programming and Problem Solving",
        "CourseType": "TheoryLab",
        "Credits": "3.0",
        "Grade": "D",
        "ExamMonth": "Nov-2014",
        "ResultDeclaredOn": "15-Dec-2014",
        "CourseOption": "NIL"
      },
      {
        "Slno": "71",
        "CourseCode": "ENG101",
        "CourseTitle": "English for Engineers - I",
        "CourseType": "TheoryLab",
        "Credits": "3.0",
        "Grade": "B",
        "ExamMonth": "Nov-2014",
        "ResultDeclaredOn": "15-Dec-2014",
        "CourseOption": "NIL"
      },
      {
        "Slno": "72",
        "CourseCode": "MEE101",
        "CourseTitle": "Engineering Graphics",
        "CourseType": "Lab",
        "Credits": "2.0",
        "Grade": "E",
        "ExamMonth": "Nov-2014",
        "ResultDeclaredOn": "15-Dec-2014",
        "CourseOption": "NIL"
      },
      {
        "Slno": "73",
        "CourseCode": "CSE220",
        "CourseTitle": "Data Structures and Algorithms",
        "CourseType": "TheoryLab",
        "Credits": "5.0",
        "Grade": "D",
        "ExamMonth": "Nov-2015",
        "ResultDeclaredOn": "23-Dec-2015",
        "CourseOption": "NIL"
      },
      {
        "Slno": "74",
        "CourseCode": "STS201",
        "CourseTitle": "Soft Skills",
        "CourseType": "SS",
        "Credits": "1.0",
        "Grade": "E",
        "ExamMonth": "Nov-2015",
        "ResultDeclaredOn": "02-Feb-2016",
        "CourseOption": "NIL"
      },
      {
        "Slno": "75",
        "CourseCode": "MGT307",
        "CourseTitle": "Principles of Marketing",
        "CourseType": "Theory",
        "Credits": "3.0",
        "Grade": "N",
        "ExamMonth": "Nov-2016",
        "ResultDeclaredOn": "23-Dec-2016",
        "CourseOption": "NIL"
      },
      {
        "Slno": "76",
        "CourseCode": "STS301",
        "CourseTitle": "Soft Skills",
        "CourseType": "SS",
        "Credits": "1.0",
        "Grade": "N",
        "ExamMonth": "Nov-2016",
        "ResultDeclaredOn": "03-Jan-2017",
        "CourseOption": "NIL"
      },
      {
        "Slno": "77",
        "CourseCode": "CSE221",
        "CourseTitle": "Microprocessor and Interfacing",
        "CourseType": "TheoryLab",
        "Credits": "4.0",
        "Grade": "N",
        "ExamMonth": "Nov-2017",
        "ResultDeclaredOn": "20-Dec-2017",
        "CourseOption": "NIL"
      },
      {
        "Slno": "78",
        "CourseCode": "CSE419",
        "CourseTitle": "Mobile Computing",
        "CourseType": "Theory",
        "Credits": "3.0",
        "Grade": "N",
        "ExamMonth": "Nov-2018",
        "ResultDeclaredOn": "19-Dec-2018",
        "CourseOption": "NIL"
      },
      {
        "Slno": "79",
        "CourseCode": "CSE427",
        "CourseTitle": "Large Scale Data Processing",
        "CourseType": "TheoryLab",
        "Credits": "4.0",
        "Grade": "N",
        "ExamMonth": "Nov-2018",
        "ResultDeclaredOn": "19-Dec-2018",
        "CourseOption": "NIL"
      }
    ],
    "cgpa_details": [
      {
        "CreditsRegistered": "154.0",
        "CreditsEarned": "75.0",
        "Cgpa": "2.92",
        "SGrades": "0",
        "AGrades": "1",
        "BGrades": "3",
        "CGrades": "4",
        "DGrades": "5",
        "EGrades": "11",
        "FGrades": "9",
        "NGrades": "13"
      }
    ]
  }
}