{
  "student_information": {
    "register_number": "17BLC1042",
    "name": "JHA ADARSH ASHOK"
  },
  "tables": {
    "grade_history": [
      {
        "Slno": "1",
        "CourseCode": "CHY1002",
        "CourseTitle": "Environmental Sciences",
        "CourseType": "TH",
        "Credits": "3.0",
        "Grade": "E",
        "ExamMonth": "Nov-2017",
        "ResultDeclaredOn": "19-Dec-2017",
        "CourseOption": "NIL",
        "CourseDistribUtion": "UC"
      },
      {
        "Slno": "2",
        "CourseCode": "CSE1001",
        "CourseTitle": "Problem Solving and Programming",
        "CourseType": "LO",
        "Credits": "3.0",
        "Grade": "S",
        "ExamMonth": "Nov-2017",
        "ResultDeclaredOn": "19-Dec-2017",
        "CourseOption": "NIL",
        "CourseDistribUtion": "UC"
      },
      {
        "Slno": "3",
        "CourseCode": "ECM1001",
        "CourseTitle": "Circuit Theory",
        "CourseType": "ETL",
        "Credits": "3.0",
        "Grade": "N",
        "ExamMonth": "Nov-2017",
        "ResultDeclaredOn": "20-Dec-2017",
        "CourseOption": "NIL",
        "CourseDistribUtion": "PC"
      },
      {
        "Slno": "4",
        "CourseCode": "ECM1001",
        "CourseTitle": "Circuit Theory",
        "CourseType": "ETL",
        "Credits": "3.0",
        "Grade": "N",
        "ExamMonth": "Nov-2018",
        "ResultDeclaredOn": "19-Dec-2018",
        "CourseOption": "NIL",
        "CourseDistribUtion": "PC"
      },
      {
        "Slno": "5",
        "CourseCode": "ENG1011",
        "CourseTitle": "English for Engineers",
        "CourseType": "LO",
        "Credits": "2.0",
        "Grade": "A",
        "ExamMonth": "L Nov-2017",
        "ResultDeclaredOn": "19-Dec-2017",
        "CourseOption": "NIL",
        "CourseDistribUtion": "UC"
      },
      {
        "Slno": "6",
        "CourseCode": "ESP1001",
        "CourseTitle": "ESPANOL FUNDAMENTAL",
        "CourseType": "TH",
        "Credits": "2.0",
        "Grade": "E",
        "ExamMonth": "Nov-2017",
        "ResultDeclaredOn": "19-Dec-2017",
        "CourseOption": "NIL",
        "CourseDistribUtion": "UC"
      },
      {
        "Slno": "7",
        "CourseCode": "MAT1011",
        "CourseTitle": "Calculus for Engineers",
        "CourseType": "ETL",
        "Credits": "4.0",
        "Grade": "A N",
        "ExamMonth": "Nov-2017",
        "ResultDeclaredOn": "20-Dec-2017",
        "CourseOption": "NIL",
        "CourseDistribUtion": "UC"
      },
      {
        "Slno": "8",
        "CourseCode": "PHY1701",
        "CourseTitle": "Engineering Physics",
        "CourseType": "ETL",
        "Credits": "4.0",
        "Grade": "N",
        "ExamMonth": "Nov-2017",
        "ResultDeclaredOn": "20-Dec-2017",
        "CourseOption": "NIL",
        "CourseDistribUtion": "UC"
      },
      {
        "Slno": "9",
        "CourseCode": "STS1001",
        "CourseTitle": "Introduction to Soft Skills",
        "CourseType": "SS",
        "Credits": "1.0",
        "Grade": "C",
        "ExamMonth": "Nov-2017",
        "ResultDeclaredOn": "28-Dec-2017",
        "CourseOption": "NIL",
        "CourseDistribUtion": "UC"
      },
      {
        "Slno": "10",
        "CourseCode": "CHY1701",
        "CourseTitle": "Engineering Chemistry",
        "CourseType": "ETL",
        "Credits": "4.0",
        "Grade": "I N",
        "ExamMonth": "Apr-2018",
        "ResultDeclaredOn": "09-May-2018",
        "CourseOption": "NIL",
        "CourseDistribUtion": "UC"
      },
      {
        "Slno": "11",
        "CourseCode": "CSE1002",
        "CourseTitle": "Problem Solving and Object Oriented Programming",
        "CourseType": "LO",
        "Credits": "C 3.0",
        "Grade": "D",
        "ExamMonth": "Apr-2018",
        "ResultDeclaredOn": "09-May-2018",
        "CourseOption": "NIL",
        "CourseDistribUtion": "UC"
      },
      {
        "Slno": "12",
        "CourseCode": "ECE1002",
        "CourseTitle": "Semiconductor Devices and Circuits",
        "CourseType": "ETL",
        "Credits": "I 4.0",
        "Grade": "C",
        "ExamMonth": "Apr-2018",
        "ResultDeclaredOn": "09-May-2018",
        "CourseOption": "NIL",
        "CourseDistribUtion": "PC"
      },
      {
        "Slno": "13",
        "CourseCode": "ECE1004",
        "CourseTitle": "Signals and Systems",
        "CourseType": "ETP",
        "Credits": "3.0",
        "Grade": "N",
        "ExamMonth": "Apr-2018",
        "ResultDeclaredOn": "09-May-2018",
        "CourseOption": "NIL",
        "CourseDistribUtion": "PC"
      },
      {
        "Slno": "14",
        "CourseCode": "HUM1021",
        "CourseTitle": "Ethics and Values",
        "CourseType": "TH",
        "Credits": "F 2.0",
        "Grade": "B",
        "ExamMonth": "Apr-2018",
        "ResultDeclaredOn": "09-May-2018",
        "CourseOption": "NIL",
        "CourseDistribUtion": "UC"
      },
      {
        "Slno": "15",
        "CourseCode": "MAT2002",
        "CourseTitle": "Applications of Differential and Difference Equations",
        "CourseType": "F ETL",
        "Credits": "4.0",
        "Grade": "N",
        "ExamMonth": "Apr-2018",
        "ResultDeclaredOn": "09-May-2018",
        "CourseOption": "NIL",
        "CourseDistribUtion": "PC"
      },
      {
        "Slno": "16",
        "CourseCode": "PHY1999",
        "CourseTitle": "Introduction to Innovative Projects",
        "CourseType": "ETP",
        "Credits": "2.0",
        "Grade": "C",
        "ExamMonth": "Apr-2018",
        "ResultDeclaredOn": "09-May-2018",
        "CourseOption": "NIL",
        "CourseDistribUtion": "UC"
      },
      {
        "Slno": "17",
        "CourseCode": "STS1002",
        "CourseTitle": "O Introduction to Business Communication",
        "CourseType": "SS",
        "Credits": "1.0",
        "Grade": "C",
        "ExamMonth": "Apr-2018",
        "ResultDeclaredOn": "09-May-2018",
        "CourseOption": "NIL",
        "CourseDistribUtion": "UC"
      },
      {
        "Slno": "18",
        "CourseCode": "ECE2002",
        "CourseTitle": "Analog Electronic Circuits",
        "CourseType": "ETLP",
        "Credits": "4.0",
        "Grade": "N",
        "ExamMonth": "Nov-2018",
        "ResultDeclaredOn": "19-Dec-2018",
        "CourseOption": "NIL",
        "CourseDistribUtion": "PC"
      },
      {
        "Slno": "19",
        "CourseCode": "ECE2003",
        "CourseTitle": "N Digital Logic Design",
        "CourseType": "ETL",
        "Credits": "3.0",
        "Grade": "N",
        "ExamMonth": "Nov-2018",
        "ResultDeclaredOn": "19-Dec-2018",
        "CourseOption": "NIL",
        "CourseDistribUtion": "PC"
      },
      {
        "Slno": "20",
        "CourseCode": "ECM1002",
        "CourseTitle": "Analysis of Data Structures and Algorithms",
        "CourseType": "ETL",
        "Credits": "4.0",
        "Grade": "N",
        "ExamMonth": "Nov-2018",
        "ResultDeclaredOn": "19-Dec-2018",
        "CourseOption": "NIL",
        "CourseDistribUtion": "PC"
      },
      {
        "Slno": "21",
        "CourseCode": "ECM1005",
        "CourseTitle": "U Principles of Software Engineering",
        "CourseType": "ETP",
        "Credits": "4.0",
        "Grade": "N",
        "ExamMonth": "Nov-2018",
        "ResultDeclaredOn": "19-Dec-2018",
        "CourseOption": "NIL",
        "CourseDistribUtion": "PE"
      },
      {
        "Slno": "22",
        "CourseCode": "MAT1014",
        "CourseTitle": "Discrete Mathematics and Graph Theory",
        "CourseType": "TH",
        "Credits": "4.0",
        "Grade": "N2",
        "ExamMonth": "Nov-2018",
        "ResultDeclaredOn": "19-Dec-2018",
        "CourseOption": "NIL",
        "CourseDistribUtion": "PC"
      },
      {
        "Slno": "23",
        "CourseCode": "MAT2001",
        "CourseTitle": "Statistics for Engineers",
        "CourseType": "ETL",
        "Credits": "4.0",
        "Grade": "N",
        "ExamMonth": "Nov-2018",
        "ResultDeclaredOn": "19-Dec-2018",
        "CourseOption": "NIL",
        "CourseDistribUtion": "UC"
      },
      {
        "Slno": "24",
        "CourseCode": "STS2001",
        "CourseTitle": "Reasoning Skill Enhancement",
        "CourseType": "SS",
        "Credits": "1.0",
        "Grade": "N3",
        "ExamMonth": "Nov-2018",
        "ResultDeclaredOn": "19-Dec-2018",
        "CourseOption": "NIL",
        "CourseDistribUtion": "UC"
      },
      {
        "Slno": "25",
        "CourseCode": "EXC1014",
        "CourseTitle": "The Art of Acting(Dramatics Club)",
        "CourseType": "ECA",
        "Credits": "2.0",
        "Grade": "P",
        "ExamMonth": "Apr-2019",
        "ResultDeclaredOn": "11-Jul-2019",
        "CourseOption": "NIL",
        "CourseDistribUtion": "UC"
      }
    ],
    "curriculum_details": [
      {
        "CurriculumDistributionType": "Programme Core",
        "CreditsRequired": "59.0",
        "CreditsEarned": "4.0"
      }
    ],
    "curriculum_details_1": [
      {
        "ProgrammeElective": "University Core",
        "390": "70.0",
        "00": "21.0"
      },
      {
        "ProgrammeElective": "University Elective",
        "390": "12.0",
        "00": "0.0"
      },
      {
        "ProgrammeElective": "Bridge Course",
        "390": "0.0",
        "00": "0.0"
      },
      {
        "ProgrammeElective": "Total Credits",
        "390": "180.0",
        "00": "25.0"
      }
    ],
    "l_basket_details": [
      {
        "BasketTitle": "Soft Skills",
        "DistributionType": "UC",
        "CreditsRequired": "6.0",
        "CreditsEarned": "2.0"
      },
      {
        "BasketTitle": "Co-Extra Curricular Basket",
        "DistributionType": "A UC",
        "CreditsRequired": "2.0",
        "CreditsEarned": "2.0"
      },
      {
        "BasketTitle": "Foreign Language Course Basket",
        "DistributionType": "UC",
        "CreditsRequired": "2.0",
        "CreditsEarned": "2.0"
      }
    ],
    "cgpa_details": [
      {
        "CreditsRegistered": "71.0",
        "CreditsEarned": "25.0",
        "Cgpa": "2.36",
        "SGrades": "1",
        "AGrades": "1",
        "CBGrades": "1",
        "CGrades": "4",
        "DGrades": "1",
        "EGrades": "2",
        "FGrades": "0",
        "NGrades": "13"
      }
    ]
  }
}