{
  "student_information": {
    "register_number": "22PHD1105",
    "name": "BALAKUMAR I"
  },
  "tables": {
    "grade_history": [
      {
        "Slno": "1",
        "CourseCode": "RES701",
        "CourseTitle": "Research Methodology- SELECT",
        "CourseType": "RM",
        "Credits": "3.0",
        "Grade": "B",
        "ExamMonth": "Feb-2023",
        "ResultDeclaredOn": "28-Feb-2023",
        "CourseOption": "NIL"
      },
      {
        "Slno": "2",
        "CourseCode": "RMC0001",
        "CourseTitle": "Research and Publication Ethics-SELECT",
        "CourseType": "RMC",
        "Credits": "3.0",
        "Grade": "C",
        "ExamMonth": "Feb-2023",
        "ResultDeclaredOn": "28-Feb-2023",
        "CourseOption": "NIL"
      },
      {
        "Slno": "3",
        "CourseCode": "RSS00484",
        "CourseTitle": "EMERGING TECHNOLOGIES IN MICROGROD",
        "CourseType": "Regular",
        "Credits": "3.0",
        "Grade": "A",
        "ExamMonth": "Jul-2023",
        "ResultDeclaredOn": "31-Jul-2023",
        "CourseOption": "NIL"
      },
      {
        "Slno": "4",
        "CourseCode": "RSS00485",
        "CourseTitle": "COMMUNICATION NETWORK FOR SMARTGRID",
        "CourseType": "Regular",
        "Credits": "3.0",
        "Grade": "S",
        "ExamMonth": "Jul-2023",
        "ResultDeclaredOn": "31-Jul-2023",
        "CourseOption": "NIL"
      },
      {
        "Slno": "5",
        "CourseCode": "MCSE602L",
        "CourseTitle": "Machine Learning",
        "CourseType": "Theory",
        "Credits": "2.0",
        "Grade": "C",
        "ExamMonth": "Dec-2023",
        "ResultDeclaredOn": "31-Dec-2023",
        "CourseOption": "NIL"
      },
      {
        "Slno": "6",
        "CourseCode": "MCSE602P",
        "CourseTitle": "Machine Learning Lab",
        "CourseType": "Lab",
        "Credits": "1.0",
        "Grade": "A",
        "ExamMonth": "Dec-2023",
        "ResultDeclaredOn": "31-Dec-2023",
        "CourseOption": "NIL"
      }
    ],
    "cgpa_details": [
      {
        "CreditsRegistered": "15.0",
        "CreditsEarned": "15.0",
        "Cgpa": "8.33",
        "SGrades": "1",
        "AGrades": "2",
        "BGrades": "1",
        "CGrades": "2",
        "DGrades": "0",
        "EGrades": "0",
        "FGrades": "0",
        "NGrades": "0"
      }
    ]
  }
}