{
  "student_information": {
    "register_number": "16BEC1062",
    "name": "SOMESH KUMAR DAS"
  },
  "tables": {
    "grade_history_combined": [
      {
        "Slno": "1",
        "CourseCode": "CHY1001",
        "CourseTitle": "Engineering Chemistry",
        "CourseType": "ETLP",
        "Credits": "5.0",
        "Grade": "B",
        "ExamMonth": "Nov-2016",
        "ResultDeclaredOn": "23-Dec-2016",
        "CourseOption": "NIL",
        "CourseDistribUtion": "UC"
      },
      {
        "Slno": "2",
        "CourseCode": "CSE1001",
        "CourseTitle": "Problem Solving and Programming",
        "CourseType": "LO",
        "Credits": "3.0",
        "Grade": "A",
        "ExamMonth": "Nov-2016",
        "ResultDeclaredOn": "23-Dec-2016",
        "CourseOption": "NIL",
        "CourseDistribUtion": "UC"
      },
      {
        "Slno": "3",
        "CourseCode": "ECE1001",
        "CourseTitle": "Fundamentals of Electrical Circuits",
        "CourseType": "ETL",
        "Credits": "3.0",
        "Grade": "B",
        "ExamMonth": "Nov-2016",
        "ResultDeclaredOn": "23-Dec-2016",
        "CourseOption": "NIL",
        "CourseDistribUtion": "PC"
      },
      {
        "Slno": "4",
        "CourseCode": "ENG1011",
        "CourseTitle": "English for Engineers",
        "CourseType": "ELP",
        "Credits": "2.0",
        "Grade": "A",
        "ExamMonth": "L Nov-2016",
        "ResultDeclaredOn": "27-Dec-2016",
        "CourseOption": "NIL",
        "CourseDistribUtion": "UC"
      },
      {
        "Slno": "5",
        "CourseCode": "HUM1021",
        "CourseTitle": "Ethics and Values",
        "CourseType": "ETP",
        "Credits": "2.0",
        "Grade": "B",
        "ExamMonth": "Nov-2016",
        "ResultDeclaredOn": "23-Dec-2016",
        "CourseOption": "NIL",
        "CourseDistribUtion": "UC"
      },
      {
        "Slno": "6",
        "CourseCode": "MAT1011",
        "CourseTitle": "Calculus for Engineers",
        "CourseType": "ETL",
        "Credits": "4.0",
        "Grade": "B",
        "ExamMonth": "Nov-2016",
        "ResultDeclaredOn": "23-Dec-2016",
        "CourseOption": "NIL",
        "CourseDistribUtion": "UC"
      },
      {
        "Slno": "7",
        "CourseCode": "PHY1001",
        "CourseTitle": "Engineering Physics",
        "CourseType": "ETLP",
        "Credits": "5.0",
        "Grade": "A A",
        "ExamMonth": "Nov-2016",
        "ResultDeclaredOn": "26-Dec-2016",
        "CourseOption": "NIL",
        "CourseDistribUtion": "UC"
      },
      {
        "Slno": "8",
        "CourseCode": "CHY1002",
        "CourseTitle": "Environmental Sciences",
        "CourseType": "ETP",
        "Credits": "3.0",
        "Grade": "A",
        "ExamMonth": "May-2017",
        "ResultDeclaredOn": "19-Jun-2017",
        "CourseOption": "NIL",
        "CourseDistribUtion": "UC"
      },
      {
        "Slno": "9",
        "CourseCode": "ECE1002",
        "CourseTitle": "Semiconductor Devices and Circuits",
        "CourseType": "ETP",
        "Credits": "4.0",
        "Grade": "I A",
        "ExamMonth": "May-2017",
        "ResultDeclaredOn": "19-Jun-2017",
        "CourseOption": "NIL",
        "CourseDistribUtion": "PC"
      },
      {
        "Slno": "10",
        "CourseCode": "ECE1005",
        "CourseTitle": "Sensors and Instrumentation",
        "CourseType": "ETP",
        "Credits": "C 2.0",
        "Grade": "C",
        "ExamMonth": "May-2017",
        "ResultDeclaredOn": "01-Jul-2017",
        "CourseOption": "NIL",
        "CourseDistribUtion": "PC"
      },
      {
        "Slno": "11",
        "CourseCode": "ECE1008",
        "CourseTitle": "Electronics Hardware Trouble Shooting",
        "CourseType": "LO",
        "Credits": "1.0",
        "Grade": "S",
        "ExamMonth": "May-2017",
        "ResultDeclaredOn": "19-Jun-2017",
        "CourseOption": "NIL",
        "CourseDistribUtion": "PE"
      },
      {
        "Slno": "12",
        "CourseCode": "ECE2001",
        "CourseTitle": "Network Theory",
        "CourseType": "ETP",
        "Credits": "I 3.0",
        "Grade": "B",
        "ExamMonth": "May-2017",
        "ResultDeclaredOn": "19-Jun-2017",
        "CourseOption": "NIL",
        "CourseDistribUtion": "PC"
      },
      {
        "Slno": "13",
        "CourseCode": "FRE1001",
        "CourseTitle": "Francais quotidien",
        "CourseType": "TH",
        "Credits": "2.0",
        "Grade": "B",
        "ExamMonth": "May-2017",
        "ResultDeclaredOn": "19-Jun-2017",
        "CourseOption": "NIL",
        "CourseDistribUtion": "UC"
      },
      {
        "Slno": "14",
        "CourseCode": "MAT2002",
        "CourseTitle": "Applications of Differential and Difference Equations",
        "CourseType": "ETL",
        "Credits": "F 4.0",
        "Grade": "A",
        "ExamMonth": "May-2017",
        "ResultDeclaredOn": "19-Jun-2017",
        "CourseOption": "NIL",
        "CourseDistribUtion": "PC"
      },
      {
        "Slno": "15",
        "CourseCode": "PHY1999",
        "CourseTitle": "Introduction to Innovative Projects",
        "CourseType": "F ETP",
        "Credits": "2.0",
        "Grade": "B",
        "ExamMonth": "May-2017",
        "ResultDeclaredOn": "08-Jul-2017",
        "CourseOption": "NIL",
        "CourseDistribUtion": "UC"
      },
      {
        "Slno": "16",
        "CourseCode": "STS1001",
        "CourseTitle": "Soft Skills",
        "CourseType": "SS",
        "Credits": "1.0",
        "Grade": "B",
        "ExamMonth": "May-2017",
        "ResultDeclaredOn": "14-Jun-2017",
        "CourseOption": "NIL",
        "CourseDistribUtion": "UC"
      },
      {
        "Slno": "17",
        "CourseCode": "ECE1003",
        "CourseTitle": "O Electromagnetic Field Theory",
        "CourseType": "ETP",
        "Credits": "3.0",
        "Grade": "S",
        "ExamMonth": "Nov-2017",
        "ResultDeclaredOn": "21-Dec-2017",
        "CourseOption": "NIL",
        "CourseDistribUtion": "PC"
      },
      {
        "Slno": "18",
        "CourseCode": "ECE1004",
        "CourseTitle": "Signals and Systems",
        "CourseType": "ETP",
        "Credits": "3.0",
        "Grade": "A",
        "ExamMonth": "Nov-2017",
        "ResultDeclaredOn": "20-Feb-2018",
        "CourseOption": "NIL",
        "CourseDistribUtion": "PC"
      },
      {
        "Slno": "19",
        "CourseCode": "ECE2002",
        "CourseTitle": "N Analog Electronic Circuits",
        "CourseType": "ETLP",
        "Credits": "4.0",
        "Grade": "A",
        "ExamMonth": "Nov-2017",
        "ResultDeclaredOn": "20-Dec-2017",
        "CourseOption": "NIL",
        "CourseDistribUtion": "PC"
      },
      {
        "Slno": "20",
        "CourseCode": "ECE2003",
        "CourseTitle": "Digital Logic Design",
        "CourseType": "ETL",
        "Credits": "3.0",
        "Grade": "C",
        "ExamMonth": "Nov-2017",
        "ResultDeclaredOn": "20-Dec-2017",
        "CourseOption": "NIL",
        "CourseDistribUtion": "PC"
      },
      {
        "Slno": "21",
        "CourseCode": "MAT2001",
        "CourseTitle": "Statistics for Engineers",
        "CourseType": "ETL",
        "Credits": "4.0",
        "Grade": "A",
        "ExamMonth": "Nov-2017",
        "ResultDeclaredOn": "20-Dec-2017",
        "CourseOption": "NIL",
        "CourseDistribUtion": "UC"
      },
      {
        "Slno": "22",
        "CourseCode": "MAT3004",
        "CourseTitle": "U Applied Linear Algebra",
        "CourseType": "TH",
        "Credits": "4.0",
        "Grade": "A",
        "ExamMonth": "Nov-2017",
        "ResultDeclaredOn": "19-Dec-2017",
        "CourseOption": "NIL",
        "CourseDistribUtion": "PC"
      },
      {
        "Slno": "23",
        "CourseCode": "STS2001",
        "CourseTitle": "Soft Skills",
        "CourseType": "SS",
        "Credits": "1.0",
        "Grade": "D",
        "ExamMonth": "Nov-2017",
        "ResultDeclaredOn": "28-Dec-2017",
        "CourseOption": "NIL",
        "CourseDistribUtion": "UC"
      },
      {
        "Slno": "24",
        "CourseCode": "ECE2004",
        "CourseTitle": "Transmission Lines and Waveguides",
        "CourseType": "TH",
        "Credits": "3.0",
        "Grade": "A",
        "ExamMonth": "Apr-2018",
        "ResultDeclaredOn": "09-May-2018",
        "CourseOption": "NIL",
        "CourseDistribUtion": "PC"
      },
      {
        "Slno": "25",
        "CourseCode": "ECE2005",
        "CourseTitle": "Probability Theory and Random Processes",
        "CourseType": "TH",
        "Credits": "3.0",
        "Grade": "A",
        "ExamMonth": "Apr-2018",
        "ResultDeclaredOn": "09-May-2018",
        "CourseOption": "NIL",
        "CourseDistribUtion": "PC"
      },
      {
        "Slno": "26",
        "CourseCode": "ECE3001",
        "CourseTitle": "Analog Communication Systems",
        "CourseType": "ETL",
        "Credits": "4.0",
        "Grade": "A",
        "ExamMonth": "Apr-2018",
        "ResultDeclaredOn": "09-May-2018",
        "CourseOption": "NIL",
        "CourseDistribUtion": "PC"
      },
      {
        "Slno": "27",
        "CourseCode": "ECE3003",
        "CourseTitle": "Microcontroller and its Applications",
        "CourseType": "ETLP",
        "Credits": "4.0",
        "Grade": "A",
        "ExamMonth": "Apr-2018",
        "ResultDeclaredOn": "09-May-2018",
        "CourseOption": "NIL",
        "CourseDistribUtion": "PC"
      },
      {
        "Slno": "28",
        "CourseCode": "ECE3004",
        "CourseTitle": "Computer Organization and Architectures",
        "CourseType": "TH",
        "Credits": "3.0",
        "Grade": "B",
        "ExamMonth": "Apr-2018",
        "ResultDeclaredOn": "09-May-2018",
        "CourseOption": "NIL",
        "CourseDistribUtion": "PE"
      },
      {
        "Slno": "29",
        "CourseCode": "EXC1005",
        "CourseTitle": "Conserve Energy and Environment(Energy and Environmental Protection Club)",
        "CourseType": "ECA",
        "Credits": "2.0",
        "Grade": "P",
        "ExamMonth": "Apr-2018",
        "ResultDeclaredOn": "11-May-2018",
        "CourseOption": "NIL",
        "CourseDistribUtion": "UC"
      },
      {
        "Slno": "30",
        "CourseCode": "MGT1022",
        "CourseTitle": "Lean Start-up Management",
        "CourseType": "ETP",
        "Credits": "2.0",
        "Grade": "B",
        "ExamMonth": "Apr-2018",
        "ResultDeclaredOn": "09-May-2018",
        "CourseOption": "NIL",
        "CourseDistribUtion": "UC"
      },
      {
        "Slno": "31",
        "CourseCode": "STS2002",
        "CourseTitle": "Introduction to Etiquette",
        "CourseType": "SS",
        "Credits": "1.0",
        "Grade": "B",
        "ExamMonth": "Apr-2018",
        "ResultDeclaredOn": "09-May-2018",
        "CourseOption": "NIL",
        "CourseDistribUtion": "UC"
      },
      {
        "Slno": "32",
        "CourseCode": "ECE2006",
        "CourseTitle": "Digital Signal Processing",
        "CourseType": "ETLP",
        "Credits": "4.0",
        "Grade": "A",
        "ExamMonth": "Nov-2018",
        "ResultDeclaredOn": "19-Dec-2018",
        "CourseOption": "NIL",
        "CourseDistribUtion": "PC"
      },
      {
        "Slno": "33",
        "CourseCode": "ECE2010",
        "CourseTitle": "Control Systems",
        "CourseType": "ETP",
        "Credits": "4.0",
        "Grade": "B",
        "ExamMonth": "Nov-2018",
        "ResultDeclaredOn": "19-Dec-2018",
        "CourseOption": "NIL",
        "CourseDistribUtion": "PE"
      },
      {
        "Slno": "34",
        "CourseCode": "ECE3002",
        "CourseTitle": "VLSI System Design",
        "CourseType": "ETL",
        "Credits": "4.0",
        "Grade": "B",
        "ExamMonth": "Nov-2018",
        "ResultDeclaredOn": "19-Dec-2018",
        "CourseOption": "NIL",
        "CourseDistribUtion": "PC"
      },
      {
        "Slno": "35",
        "CourseCode": "ECE3010",
        "CourseTitle": "Antennas and Wave Propagation",
        "CourseType": "TH",
        "Credits": "3.0",
        "Grade": "B",
        "ExamMonth": "L Nov-2018",
        "ResultDeclaredOn": "19-Dec-2018",
        "CourseOption": "NIL",
        "CourseDistribUtion": "PE"
      },
      {
        "Slno": "36",
        "CourseCode": "ECE3011",
        "CourseTitle": "Microwave Engineering",
        "CourseType": "ETLP",
        "Credits": "5.0",
        "Grade": "A",
        "ExamMonth": "Nov-2018",
        "ResultDeclaredOn": "19-Dec-2018",
        "CourseOption": "NIL",
        "CourseDistribUtion": "PE"
      },
      {
        "Slno": "37",
        "CourseCode": "ECE4001",
        "CourseTitle": "Digital Communication Systems",
        "CourseType": "ETL",
        "Credits": "4.0",
        "Grade": "A A",
        "ExamMonth": "Nov-2018",
        "ResultDeclaredOn": "19-Dec-2018",
        "CourseOption": "NIL",
        "CourseDistribUtion": "PC"
      },
      {
        "Slno": "38",
        "CourseCode": "EEE1003",
        "CourseTitle": "Electrical Workshop",
        "CourseType": "LO",
        "Credits": "1.0",
        "Grade": "S",
        "ExamMonth": "Nov-2018",
        "ResultDeclaredOn": "19-Dec-2018",
        "CourseOption": "NIL",
        "CourseDistribUtion": "UE"
      },
      {
        "Slno": "39",
        "CourseCode": "STS3001",
        "CourseTitle": "Preparedness for External Opportunities",
        "CourseType": "SS",
        "Credits": "1.0",
        "Grade": "I C",
        "ExamMonth": "Nov-2018",
        "ResultDeclaredOn": "19-Dec-2018",
        "CourseOption": "NIL",
        "CourseDistribUtion": "UC"
      },
      {
        "Slno": "40",
        "CourseCode": "CSE1002",
        "CourseTitle": "Problem Solving and Object Oriented Programming",
        "CourseType": "LO",
        "Credits": "C 3.0",
        "Grade": "A",
        "ExamMonth": "Apr-2019",
        "ResultDeclaredOn": "15-May-2019",
        "CourseOption": "NIL",
        "CourseDistribUtion": "UC"
      },
      {
        "Slno": "41",
        "CourseCode": "CSE2003",
        "CourseTitle": "Data Structures and Algorithms",
        "CourseType": "ETLP",
        "Credits": "I 4.0",
        "Grade": "A",
        "ExamMonth": "Apr-2019",
        "ResultDeclaredOn": "15-May-2019",
        "CourseOption": "NIL",
        "CourseDistribUtion": "PE"
      },
      {
        "Slno": "42",
        "CourseCode": "ECE3999",
        "CourseTitle": "Technical Answers for Real World Problems (TARP)",
        "CourseType": "ETP",
        "Credits": "F 3.0",
        "Grade": "S",
        "ExamMonth": "Apr-2019",
        "ResultDeclaredOn": "17-May-2019",
        "CourseOption": "NIL",
        "CourseDistribUtion": "UC"
      },
      {
        "Slno": "43",
        "CourseCode": "ECE4004",
        "CourseTitle": "Embedded C and Linux",
        "CourseType": "ETLP",
        "Credits": "5.0",
        "Grade": "B",
        "ExamMonth": "Apr-2019",
        "ResultDeclaredOn": "15-May-2019",
        "CourseOption": "NIL",
        "CourseDistribUtion": "PE"
      },
      {
        "Slno": "44",
        "CourseCode": "ECE4005",
        "CourseTitle": "Optical Communication and Networks",
        "CourseType": "F ETLP",
        "Credits": "4.0",
        "Grade": "S",
        "ExamMonth": "Apr-2019",
        "ResultDeclaredOn": "15-May-2019",
        "CourseOption": "NIL",
        "CourseDistribUtion": "PE"
      },
      {
        "Slno": "45",
        "CourseCode": "ECE4008",
        "CourseTitle": "Computer Communication",
        "CourseType": "ETL",
        "Credits": "4.0",
        "Grade": "B",
        "ExamMonth": "Apr-2019",
        "ResultDeclaredOn": "15-May-2019",
        "CourseOption": "NIL",
        "CourseDistribUtion": "PE"
      },
      {
        "Slno": "46",
        "CourseCode": "HUM1040",
        "CourseTitle": "O Indian Social Problems",
        "CourseType": "TH",
        "Credits": "3.0",
        "Grade": "B",
        "ExamMonth": "Apr-2019",
        "ResultDeclaredOn": "15-May-2019",
        "CourseOption": "NIL",
        "CourseDistribUtion": "UE"
      },
      {
        "Slno": "47",
        "CourseCode": "STS3005",
        "CourseTitle": "Code Mithra",
        "CourseType": "SS",
        "Credits": "1.0",
        "Grade": "E",
        "ExamMonth": "Apr-2019",
        "ResultDeclaredOn": "17-May-2019",
        "CourseOption": "NIL",
        "CourseDistribUtion": "UC"
      },
      {
        "Slno": "48",
        "CourseCode": "ECE3099",
        "CourseTitle": "Industrial Internship",
        "CourseType": "PJT",
        "Credits": "2.0",
        "Grade": "S",
        "ExamMonth": "Nov-2019",
        "ResultDeclaredOn": "07-Feb-2020",
        "CourseOption": "NIL",
        "CourseDistribUtion": "PC"
      },
      {
        "Slno": "49",
        "CourseCode": "ECE4007",
        "CourseTitle": "N Information Theory and Coding",
        "CourseType": "ETP",
        "Credits": "4.0",
        "Grade": "B",
        "ExamMonth": "Nov-2019",
        "ResultDeclaredOn": "07-Feb-2020",
        "CourseOption": "NIL",
        "CourseDistribUtion": "PE"
      },
      {
        "Slno": "50",
        "CourseCode": "ECE4098",
        "CourseTitle": "Comprehensive Examination",
        "CourseType": "PJT",
        "Credits": "2.0",
        "Grade": "S",
        "ExamMonth": "Nov-2019",
        "ResultDeclaredOn": "07-Feb-2020",
        "CourseOption": "NIL",
        "CourseDistribUtion": "UC"
      },
      {
        "Slno": "51",
        "CourseCode": "MGT1023",
        "CourseTitle": "U Fundamentals of Human Resource Management",
        "CourseType": "ETP",
        "Credits": "4.0",
        "Grade": "B",
        "ExamMonth": "Nov-2019",
        "ResultDeclaredOn": "07-Feb-2020",
        "CourseOption": "NIL",
        "CourseDistribUtion": "UE"
      },
      {
        "Slno": "52",
        "CourseCode": "MGT1031",
        "CourseTitle": "International Business",
        "CourseType": "ETP",
        "Credits": "4.0",
        "Grade": "A",
        "ExamMonth": "Nov-2019",
        "ResultDeclaredOn": "07-Feb-2020",
        "CourseOption": "NIL",
        "CourseDistribUtion": "UE"
      },
      {
        "Slno": "53",
        "CourseCode": "STS3007",
        "CourseTitle": "Career Skill Development",
        "CourseType": "SS",
        "Credits": "1.0",
        "Grade": "C",
        "ExamMonth": "Nov-2019",
        "ResultDeclaredOn": "07-Feb-2020",
        "CourseOption": "NIL",
        "CourseDistribUtion": "UC"
      },
      {
        "Slno": "54",
        "CourseCode": "ECE4099",
        "CourseTitle": "Co-Op / Capstone Project",
        "CourseType": "PJT",
        "Credits": "20.0",
        "Grade": "S",
        "ExamMonth": "Jun-2020",
        "ResultDeclaredOn": "13-Jun-2020",
        "CourseOption": "NIL",
        "CourseDistribUtion": "UC"
      }
    ],
    "curriculum_details": [
      {
        "CurriculumDistributionType": "Programme Core",
        "CreditsRequired": "61.0",
        "CreditsEarned": "61.0"
      },
      {
        "CurriculumDistributionType": "Programme Elective",
        "CreditsRequired": "37.0",
        "CreditsEarned": "37.0"
      },
      {
        "CurriculumDistributionType": "University Core",
        "CreditsRequired": "70.0",
        "CreditsEarned": "70.0"
      }
    ],
    "curriculum_details_1": [
      {
        "UniversityElective": "Bridge Course",
        "120": "0.0"
      },
      {
        "UniversityElective": "Total Credits",
        "120": "180.0"
      }
    ],
    "basket_details": [
      {
        "BasketTitle": "Chemistry / Biology",
        "DistributionType": "UC",
        "CreditsRequired": "5.0",
        "CreditsEarned": "5.0"
      },
      {
        "BasketTitle": "Soft Skills",
        "DistributionType": "UC",
        "CreditsRequired": "L 6.0",
        "CreditsEarned": "6.0"
      },
      {
        "BasketTitle": "Co-Extra Curricular Basket",
        "DistributionType": "UC",
        "CreditsRequired": "2.0",
        "CreditsEarned": "2.0"
      },
      {
        "BasketTitle": "Foreign Language Course Basket",
        "DistributionType": "A UC",
        "CreditsRequired": "2.0",
        "CreditsEarned": "2.0"
      }
    ],
    "i_cgpa_details": [
      {
        "CreditsRegistered": "180.0",
        "CreditsEarned": "180.0",
        "Cgpa": "8.75",
        "SGrades": "8",
        "AGrades": "20",
        "BGrades": "C 19",
        "CGrades": "4",
        "DGrades": "1",
        "EGrades": "1",
        "FGrades": "0",
        "NGrades": "0"
      }
    ]
  }
}